<?xml version="1.0" encoding="UTF-8" standalone="yes"?><sln:lista-miejscowosci xmlns:srv="http://gugik.gov.pl/schemas/slowniki-service/1.0" xmlns:sln="http://gugik.gov.pl/schemas/slowniki-schema/1.0"><sln:miejscowosc><sln:cyklZyciaOd>2015-06-30T00:00:00+02:00</sln:cyklZyciaOd><sln:gmIIPId>ee363892-717e-41fe-8f5e-aee899395608</sln:gmIIPId><sln:gmIIPPn>PL.PZGIK.200</sln:gmIIPPn><sln:gmIIPWersja>2012-09-26T21:56:57+02:00</sln:gmIIPWersja><sln:gmIdTeryt>1429011</sln:gmIdTeryt><sln:gmNazwa>Sokołów Podlaski</sln:gmNazwa><sln:miejscIIPId>394b5d82-b4f2-4238-8568-a13327b2bc0d</sln:miejscIIPId><sln:miejscIIPPn>PL.PZGIK.200</sln:miejscIIPPn><sln:miejscIIPWersja>2016-11-24T13:42:20+02:00</sln:miejscIIPWersja><sln:miejscIdTeryt>0975799</sln:miejscIdTeryt><sln:miejscNazwa>Wapniarka</sln:miejscNazwa><sln:miejscRodzaj>Inny obiekt</sln:miejscRodzaj><sln:powIIPId>37611728-15db-4f04-9740-aaceff8e4a86</sln:powIIPId><sln:powIIPPn>PL.PZGIK.200</sln:powIIPPn><sln:powIIPWersja>2012-09-27T08:13:53+02:00</sln:powIIPWersja><sln:powIdTeryt>1429</sln:powIdTeryt><sln:powNazwa>sokołowski</sln:powNazwa><sln:wojIIPId>4b6c492a-eb04-441d-a92a-f44359c06de7</sln:wojIIPId><sln:wojIIPPn>PL.PZGIK.200</sln:wojIIPPn><sln:wojIIPWersja>2012-09-27T13:45:13+02:00</sln:wojIIPWersja><sln:wojIdTeryt>14</sln:wojIdTeryt><sln:wojNazwa>mazowieckie</sln:wojNazwa></sln:miejscowosc><sln:miejscowosc><sln:cyklZyciaOd>2015-06-30T00:00:00+02:00</sln:cyklZyciaOd><sln:gmIIPId>ee363892-717e-41fe-8f5e-aee899395608</sln:gmIIPId><sln:gmIIPPn>PL.PZGIK.200</sln:gmIIPPn><sln:gmIIPWersja>2012-09-26T21:56:57+02:00</sln:gmIIPWersja><sln:gmIdTeryt>1429011</sln:gmIdTeryt><sln:gmNazwa>Sokołów Podlaski</sln:gmNazwa><sln:miejscIIPId>8f30ea41-b815-450a-a0f8-8ab3aa26e5a1</sln:miejscIIPId><sln:miejscIIPPn>PL.PZGIK.200</sln:miejscIIPPn><sln:miejscIIPWersja>2016-11-24T13:30:59+02:00</sln:miejscIIPWersja><sln:miejscIdTeryt>0975760</sln:miejscIdTeryt><sln:miejscNazwa>Sokołów Podlaski</sln:miejscNazwa><sln:miejscRodzaj>Miasto</sln:miejscRodzaj><sln:powIIPId>37611728-15db-4f04-9740-aaceff8e4a86</sln:powIIPId><sln:powIIPPn>PL.PZGIK.200</sln:powIIPPn><sln:powIIPWersja>2012-09-27T08:13:53+02:00</sln:powIIPWersja><sln:powIdTeryt>1429</sln:powIdTeryt><sln:powNazwa>sokołowski</sln:powNazwa><sln:wojIIPId>4b6c492a-eb04-441d-a92a-f44359c06de7</sln:wojIIPId><sln:wojIIPPn>PL.PZGIK.200</sln:wojIIPPn><sln:wojIIPWersja>2012-09-27T13:45:13+02:00</sln:wojIIPWersja><sln:wojIdTeryt>14</sln:wojIdTeryt><sln:wojNazwa>mazowieckie</sln:wojNazwa></sln:miejscowosc><sln:miejscowosc><sln:cyklZyciaOd>2015-06-30T00:00:00+02:00</sln:cyklZyciaOd><sln:gmIIPId>ee363892-717e-41fe-8f5e-aee899395608</sln:gmIIPId><sln:gmIIPPn>PL.PZGIK.200</sln:gmIIPPn><sln:gmIIPWersja>2012-09-26T21:56:57+02:00</sln:gmIIPWersja><sln:gmIdTeryt>1429011</sln:gmIdTeryt><sln:gmNazwa>Sokołów Podlaski</sln:gmNazwa><sln:miejscIIPId>1918d134-f084-42ea-b9e4-beb419c6a45a</sln:miejscIIPId><sln:miejscIIPPn>PL.PZGIK.200</sln:miejscIIPPn><sln:miejscIIPWersja>2016-11-24T13:47:20+02:00</sln:miejscIIPWersja><sln:miejscIdTeryt>0975807</sln:miejscIdTeryt><sln:miejscNazwa>Wesoła</sln:miejscNazwa><sln:miejscRodzaj>Inny obiekt</sln:miejscRodzaj><sln:powIIPId>37611728-15db-4f04-9740-aaceff8e4a86</sln:powIIPId><sln:powIIPPn>PL.PZGIK.200</sln:powIIPPn><sln:powIIPWersja>2012-09-27T08:13:53+02:00</sln:powIIPWersja><sln:powIdTeryt>1429</sln:powIdTeryt><sln:powNazwa>sokołowski</sln:powNazwa><sln:wojIIPId>4b6c492a-eb04-441d-a92a-f44359c06de7</sln:wojIIPId><sln:wojIIPPn>PL.PZGIK.200</sln:wojIIPPn><sln:wojIIPWersja>2012-09-27T13:45:13+02:00</sln:wojIIPWersja><sln:wojIdTeryt>14</sln:wojIdTeryt><sln:wojNazwa>mazowieckie</sln:wojNazwa></sln:miejscowosc><sln:miejscowosc><sln:cyklZyciaDo>2016-11-26T00:00:00+01:00</sln:cyklZyciaDo><sln:cyklZyciaOd>2014-09-29T00:00:00+02:00</sln:cyklZyciaOd><sln:gmIIPId>ee363892-717e-41fe-8f5e-aee899395608</sln:gmIIPId><sln:gmIIPPn>PL.PZGIK.200</sln:gmIIPPn><sln:gmIIPWersja>2012-09-26T21:56:57+02:00</sln:gmIIPWersja><sln:gmIdTeryt>1429011</sln:gmIdTeryt><sln:gmNazwa>Sokołów Podlaski</sln:gmNazwa><sln:miejscIIPId>032f5934-9db2-442d-a826-8564e739479c</sln:miejscIIPId><sln:miejscIIPPn>PL.PZGIK.200</sln:miejscIIPPn><sln:miejscIIPWersja>2016-11-24T13:34:00+02:00</sln:miejscIIPWersja><sln:miejscIdTeryt>3008069</sln:miejscIdTeryt><sln:miejscNazwa>Osiedle Wyspiańskiego</sln:miejscNazwa><sln:miejscRodzaj>Inny obiekt</sln:miejscRodzaj><sln:powIIPId>37611728-15db-4f04-9740-aaceff8e4a86</sln:powIIPId><sln:powIIPPn>PL.PZGIK.200</sln:powIIPPn><sln:powIIPWersja>2012-09-27T08:13:53+02:00</sln:powIIPWersja><sln:powIdTeryt>1429</sln:powIdTeryt><sln:powNazwa>sokołowski</sln:powNazwa><sln:wojIIPId>4b6c492a-eb04-441d-a92a-f44359c06de7</sln:wojIIPId><sln:wojIIPPn>PL.PZGIK.200</sln:wojIIPPn><sln:wojIIPWersja>2012-09-27T13:45:13+02:00</sln:wojIIPWersja><sln:wojIdTeryt>14</sln:wojIdTeryt><sln:wojNazwa>mazowieckie</sln:wojNazwa></sln:miejscowosc><sln:miejscowosc><sln:cyklZyciaOd>2015-06-30T00:00:00+02:00</sln:cyklZyciaOd><sln:gmIIPId>ee363892-717e-41fe-8f5e-aee899395608</sln:gmIIPId><sln:gmIIPPn>PL.PZGIK.200</sln:gmIIPPn><sln:gmIIPWersja>2012-09-26T21:56:57+02:00</sln:gmIIPWersja><sln:gmIdTeryt>1429011</sln:gmIdTeryt><sln:gmNazwa>Sokołów Podlaski</sln:gmNazwa><sln:miejscIIPId>13cb5b23-81e9-4147-a20f-8b6642279fff</sln:miejscIIPId><sln:miejscIIPPn>PL.PZGIK.200</sln:miejscIIPPn><sln:miejscIIPWersja>2016-11-24T13:47:19+02:00</sln:miejscIIPWersja><sln:miejscIdTeryt>0975782</sln:miejscIdTeryt><sln:miejscNazwa>Przeździatka</sln:miejscNazwa><sln:miejscRodzaj>Inny obiekt</sln:miejscRodzaj><sln:powIIPId>37611728-15db-4f04-9740-aaceff8e4a86</sln:powIIPId><sln:powIIPPn>PL.PZGIK.200</sln:powIIPPn><sln:powIIPWersja>2012-09-27T08:13:53+02:00</sln:powIIPWersja><sln:powIdTeryt>1429</sln:powIdTeryt><sln:powNazwa>sokołowski</sln:powNazwa><sln:wojIIPId>4b6c492a-eb04-441d-a92a-f44359c06de7</sln:wojIIPId><sln:wojIIPPn>PL.PZGIK.200</sln:wojIIPPn><sln:wojIIPWersja>2012-09-27T13:45:13+02:00</sln:wojIIPWersja><sln:wojIdTeryt>14</sln:wojIdTeryt><sln:wojNazwa>mazowieckie</sln:wojNazwa></sln:miejscowosc><sln:miejscowosc><sln:cyklZyciaDo>2016-11-26T00:00:00+01:00</sln:cyklZyciaDo><sln:cyklZyciaOd>2014-09-29T00:00:00+02:00</sln:cyklZyciaOd><sln:gmIIPId>ee363892-717e-41fe-8f5e-aee899395608</sln:gmIIPId><sln:gmIIPPn>PL.PZGIK.200</sln:gmIIPPn><sln:gmIIPWersja>2012-09-26T21:56:57+02:00</sln:gmIIPWersja><sln:gmIdTeryt>1429011</sln:gmIdTeryt><sln:gmNazwa>Sokołów Podlaski</sln:gmNazwa><sln:miejscIIPId>9e64620b-8d35-40e9-b679-d091a0e597ee</sln:miejscIIPId><sln:miejscIIPPn>PL.PZGIK.200</sln:miejscIIPPn><sln:miejscIIPWersja>2016-11-24T13:34:53+02:00</sln:miejscIIPWersja><sln:miejscIdTeryt>3008765</sln:miejscIdTeryt><sln:miejscNazwa>Osiedle Zory</sln:miejscNazwa><sln:miejscRodzaj>Inny obiekt</sln:miejscRodzaj><sln:powIIPId>37611728-15db-4f04-9740-aaceff8e4a86</sln:powIIPId><sln:powIIPPn>PL.PZGIK.200</sln:powIIPPn><sln:powIIPWersja>2012-09-27T08:13:53+02:00</sln:powIIPWersja><sln:powIdTeryt>1429</sln:powIdTeryt><sln:powNazwa>sokołowski</sln:powNazwa><sln:wojIIPId>4b6c492a-eb04-441d-a92a-f44359c06de7</sln:wojIIPId><sln:wojIIPPn>PL.PZGIK.200</sln:wojIIPPn><sln:wojIIPWersja>2012-09-27T13:45:13+02:00</sln:wojIIPWersja><sln:wojIdTeryt>14</sln:wojIdTeryt><sln:wojNazwa>mazowieckie</sln:wojNazwa></sln:miejscowosc><sln:miejscowosc><sln:cyklZyciaDo>2015-06-30T00:00:00+02:00</sln:cyklZyciaDo><sln:cyklZyciaOd>2014-09-29T00:00:00+02:00</sln:cyklZyciaOd><sln:gmIIPId>ee363892-717e-41fe-8f5e-aee899395608</sln:gmIIPId><sln:gmIIPPn>PL.PZGIK.200</sln:gmIIPPn><sln:gmIIPWersja>2012-09-26T21:56:57+02:00</sln:gmIIPWersja><sln:gmIdTeryt>1429011</sln:gmIdTeryt><sln:gmNazwa>Sokołów Podlaski</sln:gmNazwa><sln:miejscIIPId>1918d134-f084-42ea-b9e4-beb419c6a45a</sln:miejscIIPId><sln:miejscIIPPn>PL.PZGIK.200</sln:miejscIIPPn><sln:miejscIIPWersja>2016-11-24T13:47:21+02:00</sln:miejscIIPWersja><sln:miejscIdTeryt>0975807</sln:miejscIdTeryt><sln:miejscNazwa>Wesoła</sln:miejscNazwa><sln:miejscRodzaj>Inny obiekt</sln:miejscRodzaj><sln:powIIPId>37611728-15db-4f04-9740-aaceff8e4a86</sln:powIIPId><sln:powIIPPn>PL.PZGIK.200</sln:powIIPPn><sln:powIIPWersja>2012-09-27T08:13:53+02:00</sln:powIIPWersja><sln:powIdTeryt>1429</sln:powIdTeryt><sln:powNazwa>sokołowski</sln:powNazwa><sln:wojIIPId>4b6c492a-eb04-441d-a92a-f44359c06de7</sln:wojIIPId><sln:wojIIPPn>PL.PZGIK.200</sln:wojIIPPn><sln:wojIIPWersja>2012-09-27T13:45:13+02:00</sln:wojIIPWersja><sln:wojIdTeryt>14</sln:wojIdTeryt><sln:wojNazwa>mazowieckie</sln:wojNazwa></sln:miejscowosc><sln:miejscowosc><sln:cyklZyciaDo>2015-06-30T00:00:00+02:00</sln:cyklZyciaDo><sln:cyklZyciaOd>2014-09-29T00:00:00+02:00</sln:cyklZyciaOd><sln:gmIIPId>ee363892-717e-41fe-8f5e-aee899395608</sln:gmIIPId><sln:gmIIPPn>PL.PZGIK.200</sln:gmIIPPn><sln:gmIIPWersja>2012-09-26T21:56:57+02:00</sln:gmIIPWersja><sln:gmIdTeryt>1429011</sln:gmIdTeryt><sln:gmNazwa>Sokołów Podlaski</sln:gmNazwa><sln:miejscIIPId>8f30ea41-b815-450a-a0f8-8ab3aa26e5a1</sln:miejscIIPId><sln:miejscIIPPn>PL.PZGIK.200</sln:miejscIIPPn><sln:miejscIIPWersja>2016-11-24T13:31:00+02:00</sln:miejscIIPWersja><sln:miejscIdTeryt>0975760</sln:miejscIdTeryt><sln:miejscNazwa>Sokołów Podlaski</sln:miejscNazwa><sln:miejscRodzaj>Miasto</sln:miejscRodzaj><sln:powIIPId>37611728-15db-4f04-9740-aaceff8e4a86</sln:powIIPId><sln:powIIPPn>PL.PZGIK.200</sln:powIIPPn><sln:powIIPWersja>2012-09-27T08:13:53+02:00</sln:powIIPWersja><sln:powIdTeryt>1429</sln:powIdTeryt><sln:powNazwa>sokołowski</sln:powNazwa><sln:wojIIPId>4b6c492a-eb04-441d-a92a-f44359c06de7</sln:wojIIPId><sln:wojIIPPn>PL.PZGIK.200</sln:wojIIPPn><sln:wojIIPWersja>2012-09-27T13:45:13+02:00</sln:wojIIPWersja><sln:wojIdTeryt>14</sln:wojIdTeryt><sln:wojNazwa>mazowieckie</sln:wojNazwa></sln:miejscowosc><sln:miejscowosc><sln:cyklZyciaOd>2015-06-30T00:00:00+02:00</sln:cyklZyciaOd><sln:gmIIPId>ee363892-717e-41fe-8f5e-aee899395608</sln:gmIIPId><sln:gmIIPPn>PL.PZGIK.200</sln:gmIIPPn><sln:gmIIPWersja>2012-09-26T21:56:57+02:00</sln:gmIIPWersja><sln:gmIdTeryt>1429011</sln:gmIdTeryt><sln:gmNazwa>Sokołów Podlaski</sln:gmNazwa><sln:miejscIIPId>de799c48-ee10-4b12-a26c-4f3ed351952c</sln:miejscIIPId><sln:miejscIIPPn>PL.PZGIK.200</sln:miejscIIPPn><sln:miejscIIPWersja>2016-11-24T13:47:33+02:00</sln:miejscIIPWersja><sln:miejscIdTeryt>1058154</sln:miejscIdTeryt><sln:miejscNazwa>Podprzywózki</sln:miejscNazwa><sln:miejscRodzaj>Inny obiekt</sln:miejscRodzaj><sln:powIIPId>37611728-15db-4f04-9740-aaceff8e4a86</sln:powIIPId><sln:powIIPPn>PL.PZGIK.200</sln:powIIPPn><sln:powIIPWersja>2012-09-27T08:13:53+02:00</sln:powIIPWersja><sln:powIdTeryt>1429</sln:powIdTeryt><sln:powNazwa>sokołowski</sln:powNazwa><sln:wojIIPId>4b6c492a-eb04-441d-a92a-f44359c06de7</sln:wojIIPId><sln:wojIIPPn>PL.PZGIK.200</sln:wojIIPPn><sln:wojIIPWersja>2012-09-27T13:45:13+02:00</sln:wojIIPWersja><sln:wojIdTeryt>14</sln:wojIdTeryt><sln:wojNazwa>mazowieckie</sln:wojNazwa></sln:miejscowosc><sln:miejscowosc><sln:cyklZyciaDo>2015-06-30T00:00:00+02:00</sln:cyklZyciaDo><sln:cyklZyciaOd>2014-09-29T00:00:00+02:00</sln:cyklZyciaOd><sln:gmIIPId>ee363892-717e-41fe-8f5e-aee899395608</sln:gmIIPId><sln:gmIIPPn>PL.PZGIK.200</sln:gmIIPPn><sln:gmIIPWersja>2012-09-26T21:56:57+02:00</sln:gmIIPWersja><sln:gmIdTeryt>1429011</sln:gmIdTeryt><sln:gmNazwa>Sokołów Podlaski</sln:gmNazwa><sln:miejscIIPId>13cb5b23-81e9-4147-a20f-8b6642279fff</sln:miejscIIPId><sln:miejscIIPPn>PL.PZGIK.200</sln:miejscIIPPn><sln:miejscIIPWersja>2016-11-24T13:47:20+02:00</sln:miejscIIPWersja><sln:miejscIdTeryt>0975782</sln:miejscIdTeryt><sln:miejscNazwa>Przeździatka</sln:miejscNazwa><sln:miejscRodzaj>Inny obiekt</sln:miejscRodzaj><sln:powIIPId>37611728-15db-4f04-9740-aaceff8e4a86</sln:powIIPId><sln:powIIPPn>PL.PZGIK.200</sln:powIIPPn><sln:powIIPWersja>2012-09-27T08:13:53+02:00</sln:powIIPWersja><sln:powIdTeryt>1429</sln:powIdTeryt><sln:powNazwa>sokołowski</sln:powNazwa><sln:wojIIPId>4b6c492a-eb04-441d-a92a-f44359c06de7</sln:wojIIPId><sln:wojIIPPn>PL.PZGIK.200</sln:wojIIPPn><sln:wojIIPWersja>2012-09-27T13:45:13+02:00</sln:wojIIPWersja><sln:wojIdTeryt>14</sln:wojIdTeryt><sln:wojNazwa>mazowieckie</sln:wojNazwa></sln:miejscowosc><sln:miejscowosc><sln:cyklZyciaOd>2015-06-30T00:00:00+02:00</sln:cyklZyciaOd><sln:gmIIPId>ee363892-717e-41fe-8f5e-aee899395608</sln:gmIIPId><sln:gmIIPPn>PL.PZGIK.200</sln:gmIIPPn><sln:gmIIPWersja>2012-09-26T21:56:57+02:00</sln:gmIIPWersja><sln:gmIdTeryt>1429011</sln:gmIdTeryt><sln:gmNazwa>Sokołów Podlaski</sln:gmNazwa><sln:miejscIIPId>51c58778-f34f-4953-9a9a-41c4a6a56b9c</sln:miejscIIPId><sln:miejscIIPPn>PL.PZGIK.200</sln:miejscIIPPn><sln:miejscIIPWersja>2016-11-24T13:47:33+02:00</sln:miejscIIPWersja><sln:miejscIdTeryt>0975776</sln:miejscIdTeryt><sln:miejscNazwa>Podnieciecz</sln:miejscNazwa><sln:miejscRodzaj>Inny obiekt</sln:miejscRodzaj><sln:powIIPId>37611728-15db-4f04-9740-aaceff8e4a86</sln:powIIPId><sln:powIIPPn>PL.PZGIK.200</sln:powIIPPn><sln:powIIPWersja>2012-09-27T08:13:53+02:00</sln:powIIPWersja><sln:powIdTeryt>1429</sln:powIdTeryt><sln:powNazwa>sokołowski</sln:powNazwa><sln:wojIIPId>4b6c492a-eb04-441d-a92a-f44359c06de7</sln:wojIIPId><sln:wojIIPPn>PL.PZGIK.200</sln:wojIIPPn><sln:wojIIPWersja>2012-09-27T13:45:13+02:00</sln:wojIIPWersja><sln:wojIdTeryt>14</sln:wojIdTeryt><sln:wojNazwa>mazowieckie</sln:wojNazwa></sln:miejscowosc><sln:miejscowosc><sln:cyklZyciaDo>2015-06-30T00:00:00+02:00</sln:cyklZyciaDo><sln:cyklZyciaOd>2014-09-29T00:00:00+02:00</sln:cyklZyciaOd><sln:gmIIPId>ee363892-717e-41fe-8f5e-aee899395608</sln:gmIIPId><sln:gmIIPPn>PL.PZGIK.200</sln:gmIIPPn><sln:gmIIPWersja>2012-09-26T21:56:57+02:00</sln:gmIIPWersja><sln:gmIdTeryt>1429011</sln:gmIdTeryt><sln:gmNazwa>Sokołów Podlaski</sln:gmNazwa><sln:miejscIIPId>394b5d82-b4f2-4238-8568-a13327b2bc0d</sln:miejscIIPId><sln:miejscIIPPn>PL.PZGIK.200</sln:miejscIIPPn><sln:miejscIIPWersja>2016-11-24T13:42:21+02:00</sln:miejscIIPWersja><sln:miejscIdTeryt>3015896</sln:miejscIdTeryt><sln:miejscNazwa>Osiedle Miłosna</sln:miejscNazwa><sln:miejscRodzaj>Inny obiekt</sln:miejscRodzaj><sln:powIIPId>37611728-15db-4f04-9740-aaceff8e4a86</sln:powIIPId><sln:powIIPPn>PL.PZGIK.200</sln:powIIPPn><sln:powIIPWersja>2012-09-27T08:13:53+02:00</sln:powIIPWersja><sln:powIdTeryt>1429</sln:powIdTeryt><sln:powNazwa>sokołowski</sln:powNazwa><sln:wojIIPId>4b6c492a-eb04-441d-a92a-f44359c06de7</sln:wojIIPId><sln:wojIIPPn>PL.PZGIK.200</sln:wojIIPPn><sln:wojIIPWersja>2012-09-27T13:45:13+02:00</sln:wojIIPWersja><sln:wojIdTeryt>14</sln:wojIdTeryt><sln:wojNazwa>mazowieckie</sln:wojNazwa></sln:miejscowosc></sln:lista-miejscowosci>