<?xml version="1.0" encoding="UTF-8" standalone="yes"?><sln:lista-miejscowosci xmlns:srv="http://gugik.gov.pl/schemas/slowniki-service/1.0" xmlns:sln="http://gugik.gov.pl/schemas/slowniki-schema/1.0"><sln:miejscowosc><sln:cyklZyciaDo>2017-04-21T00:00:00+02:00</sln:cyklZyciaDo><sln:cyklZyciaOd>2016-01-27T00:00:00+01:00</sln:cyklZyciaOd><sln:gmIIPId>fef90d5f-eb23-4381-bcde-f50bc3f1cf0f</sln:gmIIPId><sln:gmIIPPn>PL.PZGIK.200</sln:gmIIPPn><sln:gmIIPWersja>2012-09-26T22:11:56+02:00</sln:gmIIPWersja><sln:gmIdTeryt>1214012</sln:gmIdTeryt><sln:gmNazwa>Koniusza</sln:gmNazwa><sln:miejscIIPId>18ef0594-5f45-4cf9-8774-c6deb31730b7</sln:miejscIIPId><sln:miejscIIPPn>PL.PZGIK.200</sln:miejscIIPPn><sln:miejscIIPWersja>2016-11-24T10:01:49+02:00</sln:miejscIIPWersja><sln:miejscIdTeryt>0322784</sln:miejscIdTeryt><sln:miejscNazwa>Biórków Mały</sln:miejscNazwa><sln:miejscRodzaj>Wieś</sln:miejscRodzaj><sln:powIIPId>adb95dd1-f39a-46c3-a2ee-c5dfb69b1d25</sln:powIIPId><sln:powIIPPn>PL.PZGIK.200</sln:powIIPPn><sln:powIIPWersja>2012-09-27T07:52:00+02:00</sln:powIIPWersja><sln:powIdTeryt>1214</sln:powIdTeryt><sln:powNazwa>proszowicki</sln:powNazwa><sln:waznyOd>2015-12-23T00:00:00+01:00</sln:waznyOd><sln:wojIIPId>dd2e3c64-f861-47cf-a3a3-e7751f272b2f</sln:wojIIPId><sln:wojIIPPn>PL.PZGIK.200</sln:wojIIPPn><sln:wojIIPWersja>2017-10-10T00:00:00+02:00</sln:wojIIPWersja><sln:wojIdTeryt>12</sln:wojIdTeryt><sln:wojNazwa>małopolskie</sln:wojNazwa></sln:miejscowosc><sln:miejscowosc><sln:cyklZyciaDo>2017-04-21T00:00:00+02:00</sln:cyklZyciaDo><sln:cyklZyciaOd>2016-01-27T00:00:00+01:00</sln:cyklZyciaOd><sln:gmIIPId>fef90d5f-eb23-4381-bcde-f50bc3f1cf0f</sln:gmIIPId><sln:gmIIPPn>PL.PZGIK.200</sln:gmIIPPn><sln:gmIIPWersja>2012-09-26T22:11:56+02:00</sln:gmIIPWersja><sln:gmIdTeryt>1214012</sln:gmIdTeryt><sln:gmNazwa>Koniusza</sln:gmNazwa><sln:miejscIIPId>f8a47725-b21f-4ec2-bc86-e0d6e5b921c1</sln:miejscIIPId><sln:miejscIIPPn>PL.PZGIK.200</sln:miejscIIPPn><sln:miejscIIPWersja>2016-11-24T10:01:49+02:00</sln:miejscIIPWersja><sln:miejscIdTeryt>0322809</sln:miejscIdTeryt><sln:miejscNazwa>Biórków Wielki</sln:miejscNazwa><sln:miejscRodzaj>Wieś</sln:miejscRodzaj><sln:powIIPId>adb95dd1-f39a-46c3-a2ee-c5dfb69b1d25</sln:powIIPId><sln:powIIPPn>PL.PZGIK.200</sln:powIIPPn><sln:powIIPWersja>2012-09-27T07:52:00+02:00</sln:powIIPWersja><sln:powIdTeryt>1214</sln:powIdTeryt><sln:powNazwa>proszowicki</sln:powNazwa><sln:waznyOd>2015-12-23T00:00:00+01:00</sln:waznyOd><sln:wojIIPId>dd2e3c64-f861-47cf-a3a3-e7751f272b2f</sln:wojIIPId><sln:wojIIPPn>PL.PZGIK.200</sln:wojIIPPn><sln:wojIIPWersja>2017-10-10T00:00:00+02:00</sln:wojIIPWersja><sln:wojIdTeryt>12</sln:wojIdTeryt><sln:wojNazwa>małopolskie</sln:wojNazwa></sln:miejscowosc><sln:miejscowosc><sln:cyklZyciaDo>2017-04-21T00:00:00+02:00</sln:cyklZyciaDo><sln:cyklZyciaOd>2016-01-27T00:00:00+01:00</sln:cyklZyciaOd><sln:gmIIPId>fef90d5f-eb23-4381-bcde-f50bc3f1cf0f</sln:gmIIPId><sln:gmIIPPn>PL.PZGIK.200</sln:gmIIPPn><sln:gmIIPWersja>2012-09-26T22:11:56+02:00</sln:gmIIPWersja><sln:gmIdTeryt>1214012</sln:gmIdTeryt><sln:gmNazwa>Koniusza</sln:gmNazwa><sln:miejscIIPId>94c1fcb1-c127-47bd-a28e-a5c8a227a5b7</sln:miejscIIPId><sln:miejscIIPPn>PL.PZGIK.200</sln:miejscIIPPn><sln:miejscIIPWersja>2016-11-24T10:01:49+02:00</sln:miejscIIPWersja><sln:miejscIdTeryt>0322821</sln:miejscIdTeryt><sln:miejscNazwa>Budziejowice</sln:miejscNazwa><sln:miejscRodzaj>Wieś</sln:miejscRodzaj><sln:powIIPId>adb95dd1-f39a-46c3-a2ee-c5dfb69b1d25</sln:powIIPId><sln:powIIPPn>PL.PZGIK.200</sln:powIIPPn><sln:powIIPWersja>2012-09-27T07:52:00+02:00</sln:powIIPWersja><sln:powIdTeryt>1214</sln:powIdTeryt><sln:powNazwa>proszowicki</sln:powNazwa><sln:waznyOd>2015-12-23T00:00:00+01:00</sln:waznyOd><sln:wojIIPId>dd2e3c64-f861-47cf-a3a3-e7751f272b2f</sln:wojIIPId><sln:wojIIPPn>PL.PZGIK.200</sln:wojIIPPn><sln:wojIIPWersja>2017-10-10T00:00:00+02:00</sln:wojIIPWersja><sln:wojIdTeryt>12</sln:wojIdTeryt><sln:wojNazwa>małopolskie</sln:wojNazwa></sln:miejscowosc><sln:miejscowosc><sln:cyklZyciaDo>2017-04-21T00:00:00+02:00</sln:cyklZyciaDo><sln:cyklZyciaOd>2016-01-27T00:00:00+01:00</sln:cyklZyciaOd><sln:gmIIPId>fef90d5f-eb23-4381-bcde-f50bc3f1cf0f</sln:gmIIPId><sln:gmIIPPn>PL.PZGIK.200</sln:gmIIPPn><sln:gmIIPWersja>2012-09-26T22:11:56+02:00</sln:gmIIPWersja><sln:gmIdTeryt>1214012</sln:gmIdTeryt><sln:gmNazwa>Koniusza</sln:gmNazwa><sln:miejscIIPId>2a3d5c19-3089-420e-9cfc-b4affdbc2576</sln:miejscIIPId><sln:miejscIIPPn>PL.PZGIK.200</sln:miejscIIPPn><sln:miejscIIPWersja>2016-11-24T10:01:49+02:00</sln:miejscIIPWersja><sln:miejscIdTeryt>0322838</sln:miejscIdTeryt><sln:miejscNazwa>Chorążyce</sln:miejscNazwa><sln:miejscRodzaj>Wieś</sln:miejscRodzaj><sln:powIIPId>adb95dd1-f39a-46c3-a2ee-c5dfb69b1d25</sln:powIIPId><sln:powIIPPn>PL.PZGIK.200</sln:powIIPPn><sln:powIIPWersja>2012-09-27T07:52:00+02:00</sln:powIIPWersja><sln:powIdTeryt>1214</sln:powIdTeryt><sln:powNazwa>proszowicki</sln:powNazwa><sln:waznyOd>2015-12-23T00:00:00+01:00</sln:waznyOd><sln:wojIIPId>dd2e3c64-f861-47cf-a3a3-e7751f272b2f</sln:wojIIPId><sln:wojIIPPn>PL.PZGIK.200</sln:wojIIPPn><sln:wojIIPWersja>2017-10-10T00:00:00+02:00</sln:wojIIPWersja><sln:wojIdTeryt>12</sln:wojIdTeryt><sln:wojNazwa>małopolskie</sln:wojNazwa></sln:miejscowosc><sln:miejscowosc><sln:cyklZyciaDo>2017-04-21T00:00:00+02:00</sln:cyklZyciaDo><sln:cyklZyciaOd>2016-01-27T00:00:00+01:00</sln:cyklZyciaOd><sln:gmIIPId>fef90d5f-eb23-4381-bcde-f50bc3f1cf0f</sln:gmIIPId><sln:gmIIPPn>PL.PZGIK.200</sln:gmIIPPn><sln:gmIIPWersja>2012-09-26T22:11:56+02:00</sln:gmIIPWersja><sln:gmIdTeryt>1214012</sln:gmIdTeryt><sln:gmNazwa>Koniusza</sln:gmNazwa><sln:miejscIIPId>4f3c1179-6cfb-43cd-9f97-df4554431653</sln:miejscIIPId><sln:miejscIIPPn>PL.PZGIK.200</sln:miejscIIPPn><sln:miejscIIPWersja>2016-11-24T10:01:49+02:00</sln:miejscIIPWersja><sln:miejscIdTeryt>0322867</sln:miejscIdTeryt><sln:miejscNazwa>Czernichów</sln:miejscNazwa><sln:miejscRodzaj>Wieś</sln:miejscRodzaj><sln:powIIPId>adb95dd1-f39a-46c3-a2ee-c5dfb69b1d25</sln:powIIPId><sln:powIIPPn>PL.PZGIK.200</sln:powIIPPn><sln:powIIPWersja>2012-09-27T07:52:00+02:00</sln:powIIPWersja><sln:powIdTeryt>1214</sln:powIdTeryt><sln:powNazwa>proszowicki</sln:powNazwa><sln:waznyOd>2015-12-23T00:00:00+01:00</sln:waznyOd><sln:wojIIPId>dd2e3c64-f861-47cf-a3a3-e7751f272b2f</sln:wojIIPId><sln:wojIIPPn>PL.PZGIK.200</sln:wojIIPPn><sln:wojIIPWersja>2017-10-10T00:00:00+02:00</sln:wojIIPWersja><sln:wojIdTeryt>12</sln:wojIdTeryt><sln:wojNazwa>małopolskie</sln:wojNazwa></sln:miejscowosc><sln:miejscowosc><sln:cyklZyciaDo>2017-04-21T00:00:00+02:00</sln:cyklZyciaDo><sln:cyklZyciaOd>2016-01-27T00:00:00+01:00</sln:cyklZyciaOd><sln:gmIIPId>fef90d5f-eb23-4381-bcde-f50bc3f1cf0f</sln:gmIIPId><sln:gmIIPPn>PL.PZGIK.200</sln:gmIIPPn><sln:gmIIPWersja>2012-09-26T22:11:56+02:00</sln:gmIIPWersja><sln:gmIdTeryt>1214012</sln:gmIdTeryt><sln:gmNazwa>Koniusza</sln:gmNazwa><sln:miejscIIPId>055d22b1-b7b2-401f-b9e8-b9d89a55e466</sln:miejscIIPId><sln:miejscIIPPn>PL.PZGIK.200</sln:miejscIIPPn><sln:miejscIIPWersja>2016-11-24T10:01:49+02:00</sln:miejscIIPWersja><sln:miejscIdTeryt>0322910</sln:miejscIdTeryt><sln:miejscNazwa>Dalewice</sln:miejscNazwa><sln:miejscRodzaj>Wieś</sln:miejscRodzaj><sln:powIIPId>adb95dd1-f39a-46c3-a2ee-c5dfb69b1d25</sln:powIIPId><sln:powIIPPn>PL.PZGIK.200</sln:powIIPPn><sln:powIIPWersja>2012-09-27T07:52:00+02:00</sln:powIIPWersja><sln:powIdTeryt>1214</sln:powIdTeryt><sln:powNazwa>proszowicki</sln:powNazwa><sln:waznyOd>2015-12-23T00:00:00+01:00</sln:waznyOd><sln:wojIIPId>dd2e3c64-f861-47cf-a3a3-e7751f272b2f</sln:wojIIPId><sln:wojIIPPn>PL.PZGIK.200</sln:wojIIPPn><sln:wojIIPWersja>2017-10-10T00:00:00+02:00</sln:wojIIPWersja><sln:wojIdTeryt>12</sln:wojIdTeryt><sln:wojNazwa>małopolskie</sln:wojNazwa></sln:miejscowosc><sln:miejscowosc><sln:cyklZyciaDo>2017-04-21T00:00:00+02:00</sln:cyklZyciaDo><sln:cyklZyciaOd>2016-01-27T00:00:00+01:00</sln:cyklZyciaOd><sln:gmIIPId>fef90d5f-eb23-4381-bcde-f50bc3f1cf0f</sln:gmIIPId><sln:gmIIPPn>PL.PZGIK.200</sln:gmIIPPn><sln:gmIIPWersja>2012-09-26T22:11:56+02:00</sln:gmIIPWersja><sln:gmIdTeryt>1214012</sln:gmIdTeryt><sln:gmNazwa>Koniusza</sln:gmNazwa><sln:miejscIIPId>98b569d2-846c-4f5b-8468-823db0ce3c9c</sln:miejscIIPId><sln:miejscIIPPn>PL.PZGIK.200</sln:miejscIIPPn><sln:miejscIIPWersja>2016-11-24T10:01:49+02:00</sln:miejscIIPWersja><sln:miejscIdTeryt>0322956</sln:miejscIdTeryt><sln:miejscNazwa>Glew</sln:miejscNazwa><sln:miejscRodzaj>Wieś</sln:miejscRodzaj><sln:powIIPId>adb95dd1-f39a-46c3-a2ee-c5dfb69b1d25</sln:powIIPId><sln:powIIPPn>PL.PZGIK.200</sln:powIIPPn><sln:powIIPWersja>2012-09-27T07:52:00+02:00</sln:powIIPWersja><sln:powIdTeryt>1214</sln:powIdTeryt><sln:powNazwa>proszowicki</sln:powNazwa><sln:waznyOd>2015-12-23T00:00:00+01:00</sln:waznyOd><sln:wojIIPId>dd2e3c64-f861-47cf-a3a3-e7751f272b2f</sln:wojIIPId><sln:wojIIPPn>PL.PZGIK.200</sln:wojIIPPn><sln:wojIIPWersja>2017-10-10T00:00:00+02:00</sln:wojIIPWersja><sln:wojIdTeryt>12</sln:wojIdTeryt><sln:wojNazwa>małopolskie</sln:wojNazwa></sln:miejscowosc><sln:miejscowosc><sln:cyklZyciaDo>2017-04-21T00:00:00+02:00</sln:cyklZyciaDo><sln:cyklZyciaOd>2016-01-27T00:00:00+01:00</sln:cyklZyciaOd><sln:gmIIPId>fef90d5f-eb23-4381-bcde-f50bc3f1cf0f</sln:gmIIPId><sln:gmIIPPn>PL.PZGIK.200</sln:gmIIPPn><sln:gmIIPWersja>2012-09-26T22:11:56+02:00</sln:gmIIPWersja><sln:gmIdTeryt>1214012</sln:gmIdTeryt><sln:gmNazwa>Koniusza</sln:gmNazwa><sln:miejscIIPId>4af400ce-b522-4267-a92a-b9bb3947c9dd</sln:miejscIIPId><sln:miejscIIPPn>PL.PZGIK.200</sln:miejscIIPPn><sln:miejscIIPWersja>2016-11-24T10:01:49+02:00</sln:miejscIIPWersja><sln:miejscIdTeryt>0322991</sln:miejscIdTeryt><sln:miejscNazwa>Glewiec</sln:miejscNazwa><sln:miejscRodzaj>Wieś</sln:miejscRodzaj><sln:powIIPId>adb95dd1-f39a-46c3-a2ee-c5dfb69b1d25</sln:powIIPId><sln:powIIPPn>PL.PZGIK.200</sln:powIIPPn><sln:powIIPWersja>2012-09-27T07:52:00+02:00</sln:powIIPWersja><sln:powIdTeryt>1214</sln:powIdTeryt><sln:powNazwa>proszowicki</sln:powNazwa><sln:waznyOd>2015-12-23T00:00:00+01:00</sln:waznyOd><sln:wojIIPId>dd2e3c64-f861-47cf-a3a3-e7751f272b2f</sln:wojIIPId><sln:wojIIPPn>PL.PZGIK.200</sln:wojIIPPn><sln:wojIIPWersja>2017-10-10T00:00:00+02:00</sln:wojIIPWersja><sln:wojIdTeryt>12</sln:wojIdTeryt><sln:wojNazwa>małopolskie</sln:wojNazwa></sln:miejscowosc><sln:miejscowosc><sln:cyklZyciaDo>2017-04-21T00:00:00+02:00</sln:cyklZyciaDo><sln:cyklZyciaOd>2016-01-27T00:00:00+01:00</sln:cyklZyciaOd><sln:gmIIPId>fef90d5f-eb23-4381-bcde-f50bc3f1cf0f</sln:gmIIPId><sln:gmIIPPn>PL.PZGIK.200</sln:gmIIPPn><sln:gmIIPWersja>2012-09-26T22:11:56+02:00</sln:gmIIPWersja><sln:gmIdTeryt>1214012</sln:gmIdTeryt><sln:gmNazwa>Koniusza</sln:gmNazwa><sln:miejscIIPId>9d4aabfe-b7d3-4e8e-8cf1-f7432ebfa6ec</sln:miejscIIPId><sln:miejscIIPPn>PL.PZGIK.200</sln:miejscIIPPn><sln:miejscIIPWersja>2016-11-24T10:01:49+02:00</sln:miejscIIPWersja><sln:miejscIdTeryt>0323039</sln:miejscIdTeryt><sln:miejscNazwa>Gnatowice</sln:miejscNazwa><sln:miejscRodzaj>Wieś</sln:miejscRodzaj><sln:powIIPId>adb95dd1-f39a-46c3-a2ee-c5dfb69b1d25</sln:powIIPId><sln:powIIPPn>PL.PZGIK.200</sln:powIIPPn><sln:powIIPWersja>2012-09-27T07:52:00+02:00</sln:powIIPWersja><sln:powIdTeryt>1214</sln:powIdTeryt><sln:powNazwa>proszowicki</sln:powNazwa><sln:waznyOd>2015-12-23T00:00:00+01:00</sln:waznyOd><sln:wojIIPId>dd2e3c64-f861-47cf-a3a3-e7751f272b2f</sln:wojIIPId><sln:wojIIPPn>PL.PZGIK.200</sln:wojIIPPn><sln:wojIIPWersja>2017-10-10T00:00:00+02:00</sln:wojIIPWersja><sln:wojIdTeryt>12</sln:wojIdTeryt><sln:wojNazwa>małopolskie</sln:wojNazwa></sln:miejscowosc><sln:miejscowosc><sln:cyklZyciaDo>2017-04-21T00:00:00+02:00</sln:cyklZyciaDo><sln:cyklZyciaOd>2016-01-27T00:00:00+01:00</sln:cyklZyciaOd><sln:gmIIPId>fef90d5f-eb23-4381-bcde-f50bc3f1cf0f</sln:gmIIPId><sln:gmIIPPn>PL.PZGIK.200</sln:gmIIPPn><sln:gmIIPWersja>2012-09-26T22:11:56+02:00</sln:gmIIPWersja><sln:gmIdTeryt>1214012</sln:gmIdTeryt><sln:gmNazwa>Koniusza</sln:gmNazwa><sln:miejscIIPId>c7d929b2-32f2-4a95-8389-2c9a8713baf4</sln:miejscIIPId><sln:miejscIIPPn>PL.PZGIK.200</sln:miejscIIPPn><sln:miejscIIPWersja>2016-11-24T10:01:49+02:00</sln:miejscIIPWersja><sln:miejscIdTeryt>0323080</sln:miejscIdTeryt><sln:miejscNazwa>Górka Jaklińska</sln:miejscNazwa><sln:miejscRodzaj>Wieś</sln:miejscRodzaj><sln:powIIPId>adb95dd1-f39a-46c3-a2ee-c5dfb69b1d25</sln:powIIPId><sln:powIIPPn>PL.PZGIK.200</sln:powIIPPn><sln:powIIPWersja>2012-09-27T07:52:00+02:00</sln:powIIPWersja><sln:powIdTeryt>1214</sln:powIdTeryt><sln:powNazwa>proszowicki</sln:powNazwa><sln:waznyOd>2015-12-23T00:00:00+01:00</sln:waznyOd><sln:wojIIPId>dd2e3c64-f861-47cf-a3a3-e7751f272b2f</sln:wojIIPId><sln:wojIIPPn>PL.PZGIK.200</sln:wojIIPPn><sln:wojIIPWersja>2017-10-10T00:00:00+02:00</sln:wojIIPWersja><sln:wojIdTeryt>12</sln:wojIdTeryt><sln:wojNazwa>małopolskie</sln:wojNazwa></sln:miejscowosc><sln:miejscowosc><sln:cyklZyciaDo>2017-04-21T00:00:00+02:00</sln:cyklZyciaDo><sln:cyklZyciaOd>2016-01-27T00:00:00+01:00</sln:cyklZyciaOd><sln:gmIIPId>fef90d5f-eb23-4381-bcde-f50bc3f1cf0f</sln:gmIIPId><sln:gmIIPPn>PL.PZGIK.200</sln:gmIIPPn><sln:gmIIPWersja>2012-09-26T22:11:56+02:00</sln:gmIIPWersja><sln:gmIdTeryt>1214012</sln:gmIdTeryt><sln:gmNazwa>Koniusza</sln:gmNazwa><sln:miejscIIPId>22be0f2f-8380-4319-8ab0-e98acd89be8b</sln:miejscIIPId><sln:miejscIIPPn>PL.PZGIK.200</sln:miejscIIPPn><sln:miejscIIPWersja>2016-11-24T10:01:49+02:00</sln:miejscIIPWersja><sln:miejscIdTeryt>0323140</sln:miejscIdTeryt><sln:miejscNazwa>Karwin</sln:miejscNazwa><sln:miejscRodzaj>Wieś</sln:miejscRodzaj><sln:powIIPId>adb95dd1-f39a-46c3-a2ee-c5dfb69b1d25</sln:powIIPId><sln:powIIPPn>PL.PZGIK.200</sln:powIIPPn><sln:powIIPWersja>2012-09-27T07:52:00+02:00</sln:powIIPWersja><sln:powIdTeryt>1214</sln:powIdTeryt><sln:powNazwa>proszowicki</sln:powNazwa><sln:waznyOd>2015-12-23T00:00:00+01:00</sln:waznyOd><sln:wojIIPId>dd2e3c64-f861-47cf-a3a3-e7751f272b2f</sln:wojIIPId><sln:wojIIPPn>PL.PZGIK.200</sln:wojIIPPn><sln:wojIIPWersja>2017-10-10T00:00:00+02:00</sln:wojIIPWersja><sln:wojIdTeryt>12</sln:wojIdTeryt><sln:wojNazwa>małopolskie</sln:wojNazwa></sln:miejscowosc><sln:miejscowosc><sln:cyklZyciaDo>2017-04-21T00:00:00+02:00</sln:cyklZyciaDo><sln:cyklZyciaOd>2016-01-27T00:00:00+01:00</sln:cyklZyciaOd><sln:gmIIPId>fef90d5f-eb23-4381-bcde-f50bc3f1cf0f</sln:gmIIPId><sln:gmIIPPn>PL.PZGIK.200</sln:gmIIPPn><sln:gmIIPWersja>2012-09-26T22:11:56+02:00</sln:gmIIPWersja><sln:gmIdTeryt>1214012</sln:gmIdTeryt><sln:gmNazwa>Koniusza</sln:gmNazwa><sln:miejscIIPId>7437d4dc-4801-4ae8-ad06-0699280e5669</sln:miejscIIPId><sln:miejscIIPPn>PL.PZGIK.200</sln:miejscIIPPn><sln:miejscIIPWersja>2016-11-24T10:01:49+02:00</sln:miejscIIPWersja><sln:miejscIdTeryt>0323230</sln:miejscIdTeryt><sln:miejscNazwa>Koniusza</sln:miejscNazwa><sln:miejscRodzaj>Wieś</sln:miejscRodzaj><sln:powIIPId>adb95dd1-f39a-46c3-a2ee-c5dfb69b1d25</sln:powIIPId><sln:powIIPPn>PL.PZGIK.200</sln:powIIPPn><sln:powIIPWersja>2012-09-27T07:52:00+02:00</sln:powIIPWersja><sln:powIdTeryt>1214</sln:powIdTeryt><sln:powNazwa>proszowicki</sln:powNazwa><sln:waznyOd>2015-12-23T00:00:00+01:00</sln:waznyOd><sln:wojIIPId>dd2e3c64-f861-47cf-a3a3-e7751f272b2f</sln:wojIIPId><sln:wojIIPPn>PL.PZGIK.200</sln:wojIIPPn><sln:wojIIPWersja>2017-10-10T00:00:00+02:00</sln:wojIIPWersja><sln:wojIdTeryt>12</sln:wojIdTeryt><sln:wojNazwa>małopolskie</sln:wojNazwa></sln:miejscowosc><sln:miejscowosc><sln:cyklZyciaDo>2017-04-21T00:00:00+02:00</sln:cyklZyciaDo><sln:cyklZyciaOd>2016-01-27T00:00:00+01:00</sln:cyklZyciaOd><sln:gmIIPId>fef90d5f-eb23-4381-bcde-f50bc3f1cf0f</sln:gmIIPId><sln:gmIIPPn>PL.PZGIK.200</sln:gmIIPPn><sln:gmIIPWersja>2012-09-26T22:11:56+02:00</sln:gmIIPWersja><sln:gmIdTeryt>1214012</sln:gmIdTeryt><sln:gmNazwa>Koniusza</sln:gmNazwa><sln:miejscIIPId>8c66d8d0-67ed-483c-a628-b107eabcc8bc</sln:miejscIIPId><sln:miejscIIPPn>PL.PZGIK.200</sln:miejscIIPPn><sln:miejscIIPWersja>2016-11-24T10:01:49+02:00</sln:miejscIIPWersja><sln:miejscIdTeryt>0323269</sln:miejscIdTeryt><sln:miejscNazwa>Łyszkowice</sln:miejscNazwa><sln:miejscRodzaj>Wieś</sln:miejscRodzaj><sln:powIIPId>adb95dd1-f39a-46c3-a2ee-c5dfb69b1d25</sln:powIIPId><sln:powIIPPn>PL.PZGIK.200</sln:powIIPPn><sln:powIIPWersja>2012-09-27T07:52:00+02:00</sln:powIIPWersja><sln:powIdTeryt>1214</sln:powIdTeryt><sln:powNazwa>proszowicki</sln:powNazwa><sln:waznyOd>2015-12-23T00:00:00+01:00</sln:waznyOd><sln:wojIIPId>dd2e3c64-f861-47cf-a3a3-e7751f272b2f</sln:wojIIPId><sln:wojIIPPn>PL.PZGIK.200</sln:wojIIPPn><sln:wojIIPWersja>2017-10-10T00:00:00+02:00</sln:wojIIPWersja><sln:wojIdTeryt>12</sln:wojIdTeryt><sln:wojNazwa>małopolskie</sln:wojNazwa></sln:miejscowosc><sln:miejscowosc><sln:cyklZyciaDo>2017-04-21T00:00:00+02:00</sln:cyklZyciaDo><sln:cyklZyciaOd>2016-01-27T00:00:00+01:00</sln:cyklZyciaOd><sln:gmIIPId>fef90d5f-eb23-4381-bcde-f50bc3f1cf0f</sln:gmIIPId><sln:gmIIPPn>PL.PZGIK.200</sln:gmIIPPn><sln:gmIIPWersja>2012-09-26T22:11:56+02:00</sln:gmIIPWersja><sln:gmIdTeryt>1214012</sln:gmIdTeryt><sln:gmNazwa>Koniusza</sln:gmNazwa><sln:miejscIIPId>57bf956d-65c6-498e-ac7c-1b5775d28870</sln:miejscIIPId><sln:miejscIIPPn>PL.PZGIK.200</sln:miejscIIPPn><sln:miejscIIPWersja>2016-11-24T10:01:49+02:00</sln:miejscIIPWersja><sln:miejscIdTeryt>0323358</sln:miejscIdTeryt><sln:miejscNazwa>Muniaczkowice</sln:miejscNazwa><sln:miejscRodzaj>Wieś</sln:miejscRodzaj><sln:powIIPId>adb95dd1-f39a-46c3-a2ee-c5dfb69b1d25</sln:powIIPId><sln:powIIPPn>PL.PZGIK.200</sln:powIIPPn><sln:powIIPWersja>2012-09-27T07:52:00+02:00</sln:powIIPWersja><sln:powIdTeryt>1214</sln:powIdTeryt><sln:powNazwa>proszowicki</sln:powNazwa><sln:waznyOd>2015-12-23T00:00:00+01:00</sln:waznyOd><sln:wojIIPId>dd2e3c64-f861-47cf-a3a3-e7751f272b2f</sln:wojIIPId><sln:wojIIPPn>PL.PZGIK.200</sln:wojIIPPn><sln:wojIIPWersja>2017-10-10T00:00:00+02:00</sln:wojIIPWersja><sln:wojIdTeryt>12</sln:wojIdTeryt><sln:wojNazwa>małopolskie</sln:wojNazwa></sln:miejscowosc><sln:miejscowosc><sln:cyklZyciaDo>2017-04-21T00:00:00+02:00</sln:cyklZyciaDo><sln:cyklZyciaOd>2016-01-27T00:00:00+01:00</sln:cyklZyciaOd><sln:gmIIPId>fef90d5f-eb23-4381-bcde-f50bc3f1cf0f</sln:gmIIPId><sln:gmIIPPn>PL.PZGIK.200</sln:gmIIPPn><sln:gmIIPWersja>2012-09-26T22:11:56+02:00</sln:gmIIPWersja><sln:gmIdTeryt>1214012</sln:gmIdTeryt><sln:gmNazwa>Koniusza</sln:gmNazwa><sln:miejscIIPId>280f4319-a658-41e4-a26c-ae287468340c</sln:miejscIIPId><sln:miejscIIPPn>PL.PZGIK.200</sln:miejscIIPPn><sln:miejscIIPWersja>2016-11-24T10:01:49+02:00</sln:miejscIIPWersja><sln:miejscIdTeryt>0323393</sln:miejscIdTeryt><sln:miejscNazwa>Niegardów</sln:miejscNazwa><sln:miejscRodzaj>Wieś</sln:miejscRodzaj><sln:powIIPId>adb95dd1-f39a-46c3-a2ee-c5dfb69b1d25</sln:powIIPId><sln:powIIPPn>PL.PZGIK.200</sln:powIIPPn><sln:powIIPWersja>2012-09-27T07:52:00+02:00</sln:powIIPWersja><sln:powIdTeryt>1214</sln:powIdTeryt><sln:powNazwa>proszowicki</sln:powNazwa><sln:waznyOd>2015-12-23T00:00:00+01:00</sln:waznyOd><sln:wojIIPId>dd2e3c64-f861-47cf-a3a3-e7751f272b2f</sln:wojIIPId><sln:wojIIPPn>PL.PZGIK.200</sln:wojIIPPn><sln:wojIIPWersja>2017-10-10T00:00:00+02:00</sln:wojIIPWersja><sln:wojIdTeryt>12</sln:wojIdTeryt><sln:wojNazwa>małopolskie</sln:wojNazwa></sln:miejscowosc><sln:miejscowosc><sln:cyklZyciaDo>2017-04-21T00:00:00+02:00</sln:cyklZyciaDo><sln:cyklZyciaOd>2016-01-27T00:00:00+01:00</sln:cyklZyciaOd><sln:gmIIPId>fef90d5f-eb23-4381-bcde-f50bc3f1cf0f</sln:gmIIPId><sln:gmIIPPn>PL.PZGIK.200</sln:gmIIPPn><sln:gmIIPWersja>2012-09-26T22:11:56+02:00</sln:gmIIPWersja><sln:gmIdTeryt>1214012</sln:gmIdTeryt><sln:gmNazwa>Koniusza</sln:gmNazwa><sln:miejscIIPId>ad6872c8-5a90-45e1-b091-cf9d1537b928</sln:miejscIIPId><sln:miejscIIPPn>PL.PZGIK.200</sln:miejscIIPPn><sln:miejscIIPWersja>2016-11-24T10:01:49+02:00</sln:miejscIIPWersja><sln:miejscIdTeryt>0323453</sln:miejscIdTeryt><sln:miejscNazwa>Niegardów-Kolonia</sln:miejscNazwa><sln:miejscRodzaj>Wieś</sln:miejscRodzaj><sln:powIIPId>adb95dd1-f39a-46c3-a2ee-c5dfb69b1d25</sln:powIIPId><sln:powIIPPn>PL.PZGIK.200</sln:powIIPPn><sln:powIIPWersja>2012-09-27T07:52:00+02:00</sln:powIIPWersja><sln:powIdTeryt>1214</sln:powIdTeryt><sln:powNazwa>proszowicki</sln:powNazwa><sln:waznyOd>2015-12-23T00:00:00+01:00</sln:waznyOd><sln:wojIIPId>dd2e3c64-f861-47cf-a3a3-e7751f272b2f</sln:wojIIPId><sln:wojIIPPn>PL.PZGIK.200</sln:wojIIPPn><sln:wojIIPWersja>2017-10-10T00:00:00+02:00</sln:wojIIPWersja><sln:wojIdTeryt>12</sln:wojIdTeryt><sln:wojNazwa>małopolskie</sln:wojNazwa></sln:miejscowosc><sln:miejscowosc><sln:cyklZyciaDo>2017-04-21T00:00:00+02:00</sln:cyklZyciaDo><sln:cyklZyciaOd>2016-01-27T00:00:00+01:00</sln:cyklZyciaOd><sln:gmIIPId>fef90d5f-eb23-4381-bcde-f50bc3f1cf0f</sln:gmIIPId><sln:gmIIPPn>PL.PZGIK.200</sln:gmIIPPn><sln:gmIIPWersja>2012-09-26T22:11:56+02:00</sln:gmIIPWersja><sln:gmIdTeryt>1214012</sln:gmIdTeryt><sln:gmNazwa>Koniusza</sln:gmNazwa><sln:miejscIIPId>fca87a69-3d24-49ca-81fe-295912442921</sln:miejscIIPId><sln:miejscIIPPn>PL.PZGIK.200</sln:miejscIIPPn><sln:miejscIIPWersja>2016-11-24T10:01:49+02:00</sln:miejscIIPWersja><sln:miejscIdTeryt>0323499</sln:miejscIdTeryt><sln:miejscNazwa>Piotrkowice Małe</sln:miejscNazwa><sln:miejscRodzaj>Wieś</sln:miejscRodzaj><sln:powIIPId>adb95dd1-f39a-46c3-a2ee-c5dfb69b1d25</sln:powIIPId><sln:powIIPPn>PL.PZGIK.200</sln:powIIPPn><sln:powIIPWersja>2012-09-27T07:52:00+02:00</sln:powIIPWersja><sln:powIdTeryt>1214</sln:powIdTeryt><sln:powNazwa>proszowicki</sln:powNazwa><sln:waznyOd>2015-12-23T00:00:00+01:00</sln:waznyOd><sln:wojIIPId>dd2e3c64-f861-47cf-a3a3-e7751f272b2f</sln:wojIIPId><sln:wojIIPPn>PL.PZGIK.200</sln:wojIIPPn><sln:wojIIPWersja>2017-10-10T00:00:00+02:00</sln:wojIIPWersja><sln:wojIdTeryt>12</sln:wojIdTeryt><sln:wojNazwa>małopolskie</sln:wojNazwa></sln:miejscowosc><sln:miejscowosc><sln:cyklZyciaDo>2017-04-21T00:00:00+02:00</sln:cyklZyciaDo><sln:cyklZyciaOd>2016-01-27T00:00:00+01:00</sln:cyklZyciaOd><sln:gmIIPId>fef90d5f-eb23-4381-bcde-f50bc3f1cf0f</sln:gmIIPId><sln:gmIIPPn>PL.PZGIK.200</sln:gmIIPPn><sln:gmIIPWersja>2012-09-26T22:11:56+02:00</sln:gmIIPWersja><sln:gmIdTeryt>1214012</sln:gmIdTeryt><sln:gmNazwa>Koniusza</sln:gmNazwa><sln:miejscIIPId>2f3969f1-3c69-452a-abfd-35a093d63a36</sln:miejscIIPId><sln:miejscIIPPn>PL.PZGIK.200</sln:miejscIIPPn><sln:miejscIIPWersja>2016-11-24T10:01:49+02:00</sln:miejscIIPWersja><sln:miejscIdTeryt>0323536</sln:miejscIdTeryt><sln:miejscNazwa>Piotrkowice Wielkie</sln:miejscNazwa><sln:miejscRodzaj>Wieś</sln:miejscRodzaj><sln:powIIPId>adb95dd1-f39a-46c3-a2ee-c5dfb69b1d25</sln:powIIPId><sln:powIIPPn>PL.PZGIK.200</sln:powIIPPn><sln:powIIPWersja>2012-09-27T07:52:00+02:00</sln:powIIPWersja><sln:powIdTeryt>1214</sln:powIdTeryt><sln:powNazwa>proszowicki</sln:powNazwa><sln:waznyOd>2015-12-23T00:00:00+01:00</sln:waznyOd><sln:wojIIPId>dd2e3c64-f861-47cf-a3a3-e7751f272b2f</sln:wojIIPId><sln:wojIIPPn>PL.PZGIK.200</sln:wojIIPPn><sln:wojIIPWersja>2017-10-10T00:00:00+02:00</sln:wojIIPWersja><sln:wojIdTeryt>12</sln:wojIdTeryt><sln:wojNazwa>małopolskie</sln:wojNazwa></sln:miejscowosc><sln:miejscowosc><sln:cyklZyciaDo>2017-04-21T00:00:00+02:00</sln:cyklZyciaDo><sln:cyklZyciaOd>2016-01-27T00:00:00+01:00</sln:cyklZyciaOd><sln:gmIIPId>fef90d5f-eb23-4381-bcde-f50bc3f1cf0f</sln:gmIIPId><sln:gmIIPPn>PL.PZGIK.200</sln:gmIIPPn><sln:gmIIPWersja>2012-09-26T22:11:56+02:00</sln:gmIIPWersja><sln:gmIdTeryt>1214012</sln:gmIdTeryt><sln:gmNazwa>Koniusza</sln:gmNazwa><sln:miejscIIPId>96c86507-0e67-499a-aa30-f135e5d206f7</sln:miejscIIPId><sln:miejscIIPPn>PL.PZGIK.200</sln:miejscIIPPn><sln:miejscIIPWersja>2016-11-24T10:01:49+02:00</sln:miejscIIPWersja><sln:miejscIdTeryt>0323588</sln:miejscIdTeryt><sln:miejscNazwa>Polekarcice</sln:miejscNazwa><sln:miejscRodzaj>Wieś</sln:miejscRodzaj><sln:powIIPId>adb95dd1-f39a-46c3-a2ee-c5dfb69b1d25</sln:powIIPId><sln:powIIPPn>PL.PZGIK.200</sln:powIIPPn><sln:powIIPWersja>2012-09-27T07:52:00+02:00</sln:powIIPWersja><sln:powIdTeryt>1214</sln:powIdTeryt><sln:powNazwa>proszowicki</sln:powNazwa><sln:waznyOd>2015-12-23T00:00:00+01:00</sln:waznyOd><sln:wojIIPId>dd2e3c64-f861-47cf-a3a3-e7751f272b2f</sln:wojIIPId><sln:wojIIPPn>PL.PZGIK.200</sln:wojIIPPn><sln:wojIIPWersja>2017-10-10T00:00:00+02:00</sln:wojIIPWersja><sln:wojIdTeryt>12</sln:wojIdTeryt><sln:wojNazwa>małopolskie</sln:wojNazwa></sln:miejscowosc><sln:miejscowosc><sln:cyklZyciaDo>2017-04-21T00:00:00+02:00</sln:cyklZyciaDo><sln:cyklZyciaOd>2016-01-27T00:00:00+01:00</sln:cyklZyciaOd><sln:gmIIPId>fef90d5f-eb23-4381-bcde-f50bc3f1cf0f</sln:gmIIPId><sln:gmIIPPn>PL.PZGIK.200</sln:gmIIPPn><sln:gmIIPWersja>2012-09-26T22:11:56+02:00</sln:gmIIPWersja><sln:gmIdTeryt>1214012</sln:gmIdTeryt><sln:gmNazwa>Koniusza</sln:gmNazwa><sln:miejscIIPId>d5d9502b-b160-4f6c-a1d6-9c46e8bac38a</sln:miejscIIPId><sln:miejscIIPPn>PL.PZGIK.200</sln:miejscIIPPn><sln:miejscIIPWersja>2016-11-24T10:01:49+02:00</sln:miejscIIPWersja><sln:miejscIdTeryt>0323625</sln:miejscIdTeryt><sln:miejscNazwa>Posądza</sln:miejscNazwa><sln:miejscRodzaj>Wieś</sln:miejscRodzaj><sln:powIIPId>adb95dd1-f39a-46c3-a2ee-c5dfb69b1d25</sln:powIIPId><sln:powIIPPn>PL.PZGIK.200</sln:powIIPPn><sln:powIIPWersja>2012-09-27T07:52:00+02:00</sln:powIIPWersja><sln:powIdTeryt>1214</sln:powIdTeryt><sln:powNazwa>proszowicki</sln:powNazwa><sln:waznyOd>2015-12-23T00:00:00+01:00</sln:waznyOd><sln:wojIIPId>dd2e3c64-f861-47cf-a3a3-e7751f272b2f</sln:wojIIPId><sln:wojIIPPn>PL.PZGIK.200</sln:wojIIPPn><sln:wojIIPWersja>2017-10-10T00:00:00+02:00</sln:wojIIPWersja><sln:wojIdTeryt>12</sln:wojIdTeryt><sln:wojNazwa>małopolskie</sln:wojNazwa></sln:miejscowosc><sln:miejscowosc><sln:cyklZyciaDo>2017-04-21T00:00:00+02:00</sln:cyklZyciaDo><sln:cyklZyciaOd>2016-01-27T00:00:00+01:00</sln:cyklZyciaOd><sln:gmIIPId>fef90d5f-eb23-4381-bcde-f50bc3f1cf0f</sln:gmIIPId><sln:gmIIPPn>PL.PZGIK.200</sln:gmIIPPn><sln:gmIIPWersja>2012-09-26T22:11:56+02:00</sln:gmIIPWersja><sln:gmIdTeryt>1214012</sln:gmIdTeryt><sln:gmNazwa>Koniusza</sln:gmNazwa><sln:miejscIIPId>952ae64d-d192-4205-bff8-eddc162cfe36</sln:miejscIIPId><sln:miejscIIPPn>PL.PZGIK.200</sln:miejscIIPPn><sln:miejscIIPWersja>2016-11-24T10:01:49+02:00</sln:miejscIIPWersja><sln:miejscIdTeryt>0323677</sln:miejscIdTeryt><sln:miejscNazwa>Przesławice</sln:miejscNazwa><sln:miejscRodzaj>Wieś</sln:miejscRodzaj><sln:powIIPId>adb95dd1-f39a-46c3-a2ee-c5dfb69b1d25</sln:powIIPId><sln:powIIPPn>PL.PZGIK.200</sln:powIIPPn><sln:powIIPWersja>2012-09-27T07:52:00+02:00</sln:powIIPWersja><sln:powIdTeryt>1214</sln:powIdTeryt><sln:powNazwa>proszowicki</sln:powNazwa><sln:waznyOd>2015-12-23T00:00:00+01:00</sln:waznyOd><sln:wojIIPId>dd2e3c64-f861-47cf-a3a3-e7751f272b2f</sln:wojIIPId><sln:wojIIPPn>PL.PZGIK.200</sln:wojIIPPn><sln:wojIIPWersja>2017-10-10T00:00:00+02:00</sln:wojIIPWersja><sln:wojIdTeryt>12</sln:wojIdTeryt><sln:wojNazwa>małopolskie</sln:wojNazwa></sln:miejscowosc><sln:miejscowosc><sln:cyklZyciaDo>2017-04-21T00:00:00+02:00</sln:cyklZyciaDo><sln:cyklZyciaOd>2016-01-27T00:00:00+01:00</sln:cyklZyciaOd><sln:gmIIPId>fef90d5f-eb23-4381-bcde-f50bc3f1cf0f</sln:gmIIPId><sln:gmIIPPn>PL.PZGIK.200</sln:gmIIPPn><sln:gmIIPWersja>2012-09-26T22:11:56+02:00</sln:gmIIPWersja><sln:gmIdTeryt>1214012</sln:gmIdTeryt><sln:gmNazwa>Koniusza</sln:gmNazwa><sln:miejscIIPId>f1a947fb-2d2e-4a24-ba27-95180506fec3</sln:miejscIIPId><sln:miejscIIPPn>PL.PZGIK.200</sln:miejscIIPPn><sln:miejscIIPWersja>2016-11-24T10:01:49+02:00</sln:miejscIIPWersja><sln:miejscIdTeryt>0323720</sln:miejscIdTeryt><sln:miejscNazwa>Rzędowice</sln:miejscNazwa><sln:miejscRodzaj>Wieś</sln:miejscRodzaj><sln:powIIPId>adb95dd1-f39a-46c3-a2ee-c5dfb69b1d25</sln:powIIPId><sln:powIIPPn>PL.PZGIK.200</sln:powIIPPn><sln:powIIPWersja>2012-09-27T07:52:00+02:00</sln:powIIPWersja><sln:powIdTeryt>1214</sln:powIdTeryt><sln:powNazwa>proszowicki</sln:powNazwa><sln:waznyOd>2015-12-23T00:00:00+01:00</sln:waznyOd><sln:wojIIPId>dd2e3c64-f861-47cf-a3a3-e7751f272b2f</sln:wojIIPId><sln:wojIIPPn>PL.PZGIK.200</sln:wojIIPPn><sln:wojIIPWersja>2017-10-10T00:00:00+02:00</sln:wojIIPWersja><sln:wojIdTeryt>12</sln:wojIdTeryt><sln:wojNazwa>małopolskie</sln:wojNazwa></sln:miejscowosc><sln:miejscowosc><sln:cyklZyciaDo>2017-04-21T00:00:00+02:00</sln:cyklZyciaDo><sln:cyklZyciaOd>2016-01-27T00:00:00+01:00</sln:cyklZyciaOd><sln:gmIIPId>fef90d5f-eb23-4381-bcde-f50bc3f1cf0f</sln:gmIIPId><sln:gmIIPPn>PL.PZGIK.200</sln:gmIIPPn><sln:gmIIPWersja>2012-09-26T22:11:56+02:00</sln:gmIIPWersja><sln:gmIdTeryt>1214012</sln:gmIdTeryt><sln:gmNazwa>Koniusza</sln:gmNazwa><sln:miejscIIPId>c8e811af-e7ac-4939-8453-bfdb58faec51</sln:miejscIIPId><sln:miejscIIPPn>PL.PZGIK.200</sln:miejscIIPPn><sln:miejscIIPWersja>2016-11-24T10:01:49+02:00</sln:miejscIIPWersja><sln:miejscIdTeryt>0323743</sln:miejscIdTeryt><sln:miejscNazwa>Siedliska</sln:miejscNazwa><sln:miejscRodzaj>Wieś</sln:miejscRodzaj><sln:powIIPId>adb95dd1-f39a-46c3-a2ee-c5dfb69b1d25</sln:powIIPId><sln:powIIPPn>PL.PZGIK.200</sln:powIIPPn><sln:powIIPWersja>2012-09-27T07:52:00+02:00</sln:powIIPWersja><sln:powIdTeryt>1214</sln:powIdTeryt><sln:powNazwa>proszowicki</sln:powNazwa><sln:waznyOd>2015-12-23T00:00:00+01:00</sln:waznyOd><sln:wojIIPId>dd2e3c64-f861-47cf-a3a3-e7751f272b2f</sln:wojIIPId><sln:wojIIPPn>PL.PZGIK.200</sln:wojIIPPn><sln:wojIIPWersja>2017-10-10T00:00:00+02:00</sln:wojIIPWersja><sln:wojIdTeryt>12</sln:wojIdTeryt><sln:wojNazwa>małopolskie</sln:wojNazwa></sln:miejscowosc><sln:miejscowosc><sln:cyklZyciaDo>2017-04-21T00:00:00+02:00</sln:cyklZyciaDo><sln:cyklZyciaOd>2016-01-27T00:00:00+01:00</sln:cyklZyciaOd><sln:gmIIPId>fef90d5f-eb23-4381-bcde-f50bc3f1cf0f</sln:gmIIPId><sln:gmIIPPn>PL.PZGIK.200</sln:gmIIPPn><sln:gmIIPWersja>2012-09-26T22:11:56+02:00</sln:gmIIPWersja><sln:gmIdTeryt>1214012</sln:gmIdTeryt><sln:gmNazwa>Koniusza</sln:gmNazwa><sln:miejscIIPId>51615ecf-f3c8-44c9-b821-7f8d3ae23b3c</sln:miejscIIPId><sln:miejscIIPPn>PL.PZGIK.200</sln:miejscIIPPn><sln:miejscIIPWersja>2016-11-24T10:01:49+02:00</sln:miejscIIPWersja><sln:miejscIdTeryt>0323803</sln:miejscIdTeryt><sln:miejscNazwa>Szarbia</sln:miejscNazwa><sln:miejscRodzaj>Wieś</sln:miejscRodzaj><sln:powIIPId>adb95dd1-f39a-46c3-a2ee-c5dfb69b1d25</sln:powIIPId><sln:powIIPPn>PL.PZGIK.200</sln:powIIPPn><sln:powIIPWersja>2012-09-27T07:52:00+02:00</sln:powIIPWersja><sln:powIdTeryt>1214</sln:powIdTeryt><sln:powNazwa>proszowicki</sln:powNazwa><sln:waznyOd>2015-12-23T00:00:00+01:00</sln:waznyOd><sln:wojIIPId>dd2e3c64-f861-47cf-a3a3-e7751f272b2f</sln:wojIIPId><sln:wojIIPPn>PL.PZGIK.200</sln:wojIIPPn><sln:wojIIPWersja>2017-10-10T00:00:00+02:00</sln:wojIIPWersja><sln:wojIdTeryt>12</sln:wojIdTeryt><sln:wojNazwa>małopolskie</sln:wojNazwa></sln:miejscowosc><sln:miejscowosc><sln:cyklZyciaDo>2017-04-21T00:00:00+02:00</sln:cyklZyciaDo><sln:cyklZyciaOd>2016-01-27T00:00:00+01:00</sln:cyklZyciaOd><sln:gmIIPId>fef90d5f-eb23-4381-bcde-f50bc3f1cf0f</sln:gmIIPId><sln:gmIIPPn>PL.PZGIK.200</sln:gmIIPPn><sln:gmIIPWersja>2012-09-26T22:11:56+02:00</sln:gmIIPWersja><sln:gmIdTeryt>1214012</sln:gmIdTeryt><sln:gmNazwa>Koniusza</sln:gmNazwa><sln:miejscIIPId>b8198fb9-3d11-400d-beed-af536f381cb2</sln:miejscIIPId><sln:miejscIIPPn>PL.PZGIK.200</sln:miejscIIPPn><sln:miejscIIPWersja>2016-11-24T10:01:49+02:00</sln:miejscIIPWersja><sln:miejscIdTeryt>0323832</sln:miejscIdTeryt><sln:miejscNazwa>Wąsów</sln:miejscNazwa><sln:miejscRodzaj>Wieś</sln:miejscRodzaj><sln:powIIPId>adb95dd1-f39a-46c3-a2ee-c5dfb69b1d25</sln:powIIPId><sln:powIIPPn>PL.PZGIK.200</sln:powIIPPn><sln:powIIPWersja>2012-09-27T07:52:00+02:00</sln:powIIPWersja><sln:powIdTeryt>1214</sln:powIdTeryt><sln:powNazwa>proszowicki</sln:powNazwa><sln:waznyOd>2015-12-23T00:00:00+01:00</sln:waznyOd><sln:wojIIPId>dd2e3c64-f861-47cf-a3a3-e7751f272b2f</sln:wojIIPId><sln:wojIIPPn>PL.PZGIK.200</sln:wojIIPPn><sln:wojIIPWersja>2017-10-10T00:00:00+02:00</sln:wojIIPWersja><sln:wojIdTeryt>12</sln:wojIdTeryt><sln:wojNazwa>małopolskie</sln:wojNazwa></sln:miejscowosc><sln:miejscowosc><sln:cyklZyciaDo>2017-04-21T00:00:00+02:00</sln:cyklZyciaDo><sln:cyklZyciaOd>2016-01-27T00:00:00+01:00</sln:cyklZyciaOd><sln:gmIIPId>fef90d5f-eb23-4381-bcde-f50bc3f1cf0f</sln:gmIIPId><sln:gmIIPPn>PL.PZGIK.200</sln:gmIIPPn><sln:gmIIPWersja>2012-09-26T22:11:56+02:00</sln:gmIIPWersja><sln:gmIdTeryt>1214012</sln:gmIdTeryt><sln:gmNazwa>Koniusza</sln:gmNazwa><sln:miejscIIPId>5dd5f40e-ae15-4182-9600-086e57fdc881</sln:miejscIIPId><sln:miejscIIPPn>PL.PZGIK.200</sln:miejscIIPPn><sln:miejscIIPWersja>2016-11-24T10:01:49+02:00</sln:miejscIIPWersja><sln:miejscIdTeryt>0323878</sln:miejscIdTeryt><sln:miejscNazwa>Wierzbno</sln:miejscNazwa><sln:miejscRodzaj>Wieś</sln:miejscRodzaj><sln:powIIPId>adb95dd1-f39a-46c3-a2ee-c5dfb69b1d25</sln:powIIPId><sln:powIIPPn>PL.PZGIK.200</sln:powIIPPn><sln:powIIPWersja>2012-09-27T07:52:00+02:00</sln:powIIPWersja><sln:powIdTeryt>1214</sln:powIdTeryt><sln:powNazwa>proszowicki</sln:powNazwa><sln:waznyOd>2015-12-23T00:00:00+01:00</sln:waznyOd><sln:wojIIPId>dd2e3c64-f861-47cf-a3a3-e7751f272b2f</sln:wojIIPId><sln:wojIIPPn>PL.PZGIK.200</sln:wojIIPPn><sln:wojIIPWersja>2017-10-10T00:00:00+02:00</sln:wojIIPWersja><sln:wojIdTeryt>12</sln:wojIdTeryt><sln:wojNazwa>małopolskie</sln:wojNazwa></sln:miejscowosc><sln:miejscowosc><sln:cyklZyciaDo>2017-04-21T00:00:00+02:00</sln:cyklZyciaDo><sln:cyklZyciaOd>2016-01-27T00:00:00+01:00</sln:cyklZyciaOd><sln:gmIIPId>fef90d5f-eb23-4381-bcde-f50bc3f1cf0f</sln:gmIIPId><sln:gmIIPPn>PL.PZGIK.200</sln:gmIIPPn><sln:gmIIPWersja>2012-09-26T22:11:56+02:00</sln:gmIIPWersja><sln:gmIdTeryt>1214012</sln:gmIdTeryt><sln:gmNazwa>Koniusza</sln:gmNazwa><sln:miejscIIPId>b8b45435-7978-4c2e-86c1-3b7a6ea23a9d</sln:miejscIIPId><sln:miejscIIPPn>PL.PZGIK.200</sln:miejscIIPPn><sln:miejscIIPWersja>2016-11-24T10:01:49+02:00</sln:miejscIIPWersja><sln:miejscIdTeryt>0323909</sln:miejscIdTeryt><sln:miejscNazwa>Wroniec</sln:miejscNazwa><sln:miejscRodzaj>Wieś</sln:miejscRodzaj><sln:powIIPId>adb95dd1-f39a-46c3-a2ee-c5dfb69b1d25</sln:powIIPId><sln:powIIPPn>PL.PZGIK.200</sln:powIIPPn><sln:powIIPWersja>2012-09-27T07:52:00+02:00</sln:powIIPWersja><sln:powIdTeryt>1214</sln:powIdTeryt><sln:powNazwa>proszowicki</sln:powNazwa><sln:waznyOd>2015-12-23T00:00:00+01:00</sln:waznyOd><sln:wojIIPId>dd2e3c64-f861-47cf-a3a3-e7751f272b2f</sln:wojIIPId><sln:wojIIPPn>PL.PZGIK.200</sln:wojIIPPn><sln:wojIIPWersja>2017-10-10T00:00:00+02:00</sln:wojIIPWersja><sln:wojIdTeryt>12</sln:wojIdTeryt><sln:wojNazwa>małopolskie</sln:wojNazwa></sln:miejscowosc><sln:miejscowosc><sln:cyklZyciaDo>2017-04-21T00:00:00+02:00</sln:cyklZyciaDo><sln:cyklZyciaOd>2016-01-27T00:00:00+01:00</sln:cyklZyciaOd><sln:gmIIPId>fef90d5f-eb23-4381-bcde-f50bc3f1cf0f</sln:gmIIPId><sln:gmIIPPn>PL.PZGIK.200</sln:gmIIPPn><sln:gmIIPWersja>2012-09-26T22:11:56+02:00</sln:gmIIPWersja><sln:gmIdTeryt>1214012</sln:gmIdTeryt><sln:gmNazwa>Koniusza</sln:gmNazwa><sln:miejscIIPId>c74410ec-f236-4642-9544-6676ec61addb</sln:miejscIIPId><sln:miejscIIPPn>PL.PZGIK.200</sln:miejscIIPPn><sln:miejscIIPWersja>2016-11-24T10:01:49+02:00</sln:miejscIIPWersja><sln:miejscIdTeryt>0323944</sln:miejscIdTeryt><sln:miejscNazwa>Wronin</sln:miejscNazwa><sln:miejscRodzaj>Wieś</sln:miejscRodzaj><sln:powIIPId>adb95dd1-f39a-46c3-a2ee-c5dfb69b1d25</sln:powIIPId><sln:powIIPPn>PL.PZGIK.200</sln:powIIPPn><sln:powIIPWersja>2012-09-27T07:52:00+02:00</sln:powIIPWersja><sln:powIdTeryt>1214</sln:powIdTeryt><sln:powNazwa>proszowicki</sln:powNazwa><sln:waznyOd>2015-12-23T00:00:00+01:00</sln:waznyOd><sln:wojIIPId>dd2e3c64-f861-47cf-a3a3-e7751f272b2f</sln:wojIIPId><sln:wojIIPPn>PL.PZGIK.200</sln:wojIIPPn><sln:wojIIPWersja>2017-10-10T00:00:00+02:00</sln:wojIIPWersja><sln:wojIdTeryt>12</sln:wojIdTeryt><sln:wojNazwa>małopolskie</sln:wojNazwa></sln:miejscowosc><sln:miejscowosc><sln:cyklZyciaDo>2017-04-21T00:00:00+02:00</sln:cyklZyciaDo><sln:cyklZyciaOd>2016-01-27T00:00:00+01:00</sln:cyklZyciaOd><sln:gmIIPId>fef90d5f-eb23-4381-bcde-f50bc3f1cf0f</sln:gmIIPId><sln:gmIIPPn>PL.PZGIK.200</sln:gmIIPPn><sln:gmIIPWersja>2012-09-26T22:11:56+02:00</sln:gmIIPWersja><sln:gmIdTeryt>1214012</sln:gmIdTeryt><sln:gmNazwa>Koniusza</sln:gmNazwa><sln:miejscIIPId>f7da0305-d074-4d60-bb33-7b94657556cc</sln:miejscIIPId><sln:miejscIIPPn>PL.PZGIK.200</sln:miejscIIPPn><sln:miejscIIPWersja>2016-11-24T10:01:49+02:00</sln:miejscIIPWersja><sln:miejscIdTeryt>0324027</sln:miejscIdTeryt><sln:miejscNazwa>Zielona</sln:miejscNazwa><sln:miejscRodzaj>Wieś</sln:miejscRodzaj><sln:powIIPId>adb95dd1-f39a-46c3-a2ee-c5dfb69b1d25</sln:powIIPId><sln:powIIPPn>PL.PZGIK.200</sln:powIIPPn><sln:powIIPWersja>2012-09-27T07:52:00+02:00</sln:powIIPWersja><sln:powIdTeryt>1214</sln:powIdTeryt><sln:powNazwa>proszowicki</sln:powNazwa><sln:waznyOd>2015-12-23T00:00:00+01:00</sln:waznyOd><sln:wojIIPId>dd2e3c64-f861-47cf-a3a3-e7751f272b2f</sln:wojIIPId><sln:wojIIPPn>PL.PZGIK.200</sln:wojIIPPn><sln:wojIIPWersja>2017-10-10T00:00:00+02:00</sln:wojIIPWersja><sln:wojIdTeryt>12</sln:wojIdTeryt><sln:wojNazwa>małopolskie</sln:wojNazwa></sln:miejscowosc><sln:miejscowosc><sln:cyklZyciaOd>2017-04-21T00:00:00+02:00</sln:cyklZyciaOd><sln:gmIIPId>fef90d5f-eb23-4381-bcde-f50bc3f1cf0f</sln:gmIIPId><sln:gmIIPPn>PL.PZGIK.200</sln:gmIIPPn><sln:gmIIPWersja>2012-09-26T22:11:56+02:00</sln:gmIIPWersja><sln:gmIdTeryt>1214012</sln:gmIdTeryt><sln:gmNazwa>Koniusza</sln:gmNazwa><sln:miejscIIPId>18ef0594-5f45-4cf9-8774-c6deb31730b7</sln:miejscIIPId><sln:miejscIIPPn>PL.PZGIK.200</sln:miejscIIPPn><sln:miejscIIPWersja>2017-04-21T14:09:29+02:00</sln:miejscIIPWersja><sln:miejscIdTeryt>0322784</sln:miejscIdTeryt><sln:miejscNazwa>Biórków Mały</sln:miejscNazwa><sln:miejscRodzaj>Wieś</sln:miejscRodzaj><sln:powIIPId>adb95dd1-f39a-46c3-a2ee-c5dfb69b1d25</sln:powIIPId><sln:powIIPPn>PL.PZGIK.200</sln:powIIPPn><sln:powIIPWersja>2012-09-27T07:52:00+02:00</sln:powIIPWersja><sln:powIdTeryt>1214</sln:powIdTeryt><sln:powNazwa>proszowicki</sln:powNazwa><sln:waznyOd>2015-12-23T00:00:00+01:00</sln:waznyOd><sln:wojIIPId>dd2e3c64-f861-47cf-a3a3-e7751f272b2f</sln:wojIIPId><sln:wojIIPPn>PL.PZGIK.200</sln:wojIIPPn><sln:wojIIPWersja>2017-10-10T00:00:00+02:00</sln:wojIIPWersja><sln:wojIdTeryt>12</sln:wojIdTeryt><sln:wojNazwa>małopolskie</sln:wojNazwa></sln:miejscowosc><sln:miejscowosc><sln:cyklZyciaOd>2017-04-21T00:00:00+02:00</sln:cyklZyciaOd><sln:gmIIPId>fef90d5f-eb23-4381-bcde-f50bc3f1cf0f</sln:gmIIPId><sln:gmIIPPn>PL.PZGIK.200</sln:gmIIPPn><sln:gmIIPWersja>2012-09-26T22:11:56+02:00</sln:gmIIPWersja><sln:gmIdTeryt>1214012</sln:gmIdTeryt><sln:gmNazwa>Koniusza</sln:gmNazwa><sln:miejscIIPId>f8a47725-b21f-4ec2-bc86-e0d6e5b921c1</sln:miejscIIPId><sln:miejscIIPPn>PL.PZGIK.200</sln:miejscIIPPn><sln:miejscIIPWersja>2017-04-21T14:09:35+02:00</sln:miejscIIPWersja><sln:miejscIdTeryt>0322809</sln:miejscIdTeryt><sln:miejscNazwa>Biórków Wielki</sln:miejscNazwa><sln:miejscRodzaj>Wieś</sln:miejscRodzaj><sln:powIIPId>adb95dd1-f39a-46c3-a2ee-c5dfb69b1d25</sln:powIIPId><sln:powIIPPn>PL.PZGIK.200</sln:powIIPPn><sln:powIIPWersja>2012-09-27T07:52:00+02:00</sln:powIIPWersja><sln:powIdTeryt>1214</sln:powIdTeryt><sln:powNazwa>proszowicki</sln:powNazwa><sln:waznyOd>2015-12-23T00:00:00+01:00</sln:waznyOd><sln:wojIIPId>dd2e3c64-f861-47cf-a3a3-e7751f272b2f</sln:wojIIPId><sln:wojIIPPn>PL.PZGIK.200</sln:wojIIPPn><sln:wojIIPWersja>2017-10-10T00:00:00+02:00</sln:wojIIPWersja><sln:wojIdTeryt>12</sln:wojIdTeryt><sln:wojNazwa>małopolskie</sln:wojNazwa></sln:miejscowosc><sln:miejscowosc><sln:cyklZyciaOd>2017-04-21T00:00:00+02:00</sln:cyklZyciaOd><sln:gmIIPId>fef90d5f-eb23-4381-bcde-f50bc3f1cf0f</sln:gmIIPId><sln:gmIIPPn>PL.PZGIK.200</sln:gmIIPPn><sln:gmIIPWersja>2012-09-26T22:11:56+02:00</sln:gmIIPWersja><sln:gmIdTeryt>1214012</sln:gmIdTeryt><sln:gmNazwa>Koniusza</sln:gmNazwa><sln:miejscIIPId>94c1fcb1-c127-47bd-a28e-a5c8a227a5b7</sln:miejscIIPId><sln:miejscIIPPn>PL.PZGIK.200</sln:miejscIIPPn><sln:miejscIIPWersja>2017-04-21T14:09:35+02:00</sln:miejscIIPWersja><sln:miejscIdTeryt>0322821</sln:miejscIdTeryt><sln:miejscNazwa>Budziejowice</sln:miejscNazwa><sln:miejscRodzaj>Wieś</sln:miejscRodzaj><sln:powIIPId>adb95dd1-f39a-46c3-a2ee-c5dfb69b1d25</sln:powIIPId><sln:powIIPPn>PL.PZGIK.200</sln:powIIPPn><sln:powIIPWersja>2012-09-27T07:52:00+02:00</sln:powIIPWersja><sln:powIdTeryt>1214</sln:powIdTeryt><sln:powNazwa>proszowicki</sln:powNazwa><sln:waznyOd>2015-12-23T00:00:00+01:00</sln:waznyOd><sln:wojIIPId>dd2e3c64-f861-47cf-a3a3-e7751f272b2f</sln:wojIIPId><sln:wojIIPPn>PL.PZGIK.200</sln:wojIIPPn><sln:wojIIPWersja>2017-10-10T00:00:00+02:00</sln:wojIIPWersja><sln:wojIdTeryt>12</sln:wojIdTeryt><sln:wojNazwa>małopolskie</sln:wojNazwa></sln:miejscowosc><sln:miejscowosc><sln:cyklZyciaOd>2017-04-21T00:00:00+02:00</sln:cyklZyciaOd><sln:gmIIPId>fef90d5f-eb23-4381-bcde-f50bc3f1cf0f</sln:gmIIPId><sln:gmIIPPn>PL.PZGIK.200</sln:gmIIPPn><sln:gmIIPWersja>2012-09-26T22:11:56+02:00</sln:gmIIPWersja><sln:gmIdTeryt>1214012</sln:gmIdTeryt><sln:gmNazwa>Koniusza</sln:gmNazwa><sln:miejscIIPId>2a3d5c19-3089-420e-9cfc-b4affdbc2576</sln:miejscIIPId><sln:miejscIIPPn>PL.PZGIK.200</sln:miejscIIPPn><sln:miejscIIPWersja>2017-04-21T14:09:35+02:00</sln:miejscIIPWersja><sln:miejscIdTeryt>0322838</sln:miejscIdTeryt><sln:miejscNazwa>Chorążyce</sln:miejscNazwa><sln:miejscRodzaj>Wieś</sln:miejscRodzaj><sln:powIIPId>adb95dd1-f39a-46c3-a2ee-c5dfb69b1d25</sln:powIIPId><sln:powIIPPn>PL.PZGIK.200</sln:powIIPPn><sln:powIIPWersja>2012-09-27T07:52:00+02:00</sln:powIIPWersja><sln:powIdTeryt>1214</sln:powIdTeryt><sln:powNazwa>proszowicki</sln:powNazwa><sln:waznyOd>2015-12-23T00:00:00+01:00</sln:waznyOd><sln:wojIIPId>dd2e3c64-f861-47cf-a3a3-e7751f272b2f</sln:wojIIPId><sln:wojIIPPn>PL.PZGIK.200</sln:wojIIPPn><sln:wojIIPWersja>2017-10-10T00:00:00+02:00</sln:wojIIPWersja><sln:wojIdTeryt>12</sln:wojIdTeryt><sln:wojNazwa>małopolskie</sln:wojNazwa></sln:miejscowosc><sln:miejscowosc><sln:cyklZyciaOd>2017-04-21T00:00:00+02:00</sln:cyklZyciaOd><sln:gmIIPId>fef90d5f-eb23-4381-bcde-f50bc3f1cf0f</sln:gmIIPId><sln:gmIIPPn>PL.PZGIK.200</sln:gmIIPPn><sln:gmIIPWersja>2012-09-26T22:11:56+02:00</sln:gmIIPWersja><sln:gmIdTeryt>1214012</sln:gmIdTeryt><sln:gmNazwa>Koniusza</sln:gmNazwa><sln:miejscIIPId>4f3c1179-6cfb-43cd-9f97-df4554431653</sln:miejscIIPId><sln:miejscIIPPn>PL.PZGIK.200</sln:miejscIIPPn><sln:miejscIIPWersja>2017-04-21T14:09:35+02:00</sln:miejscIIPWersja><sln:miejscIdTeryt>0322867</sln:miejscIdTeryt><sln:miejscNazwa>Czernichów</sln:miejscNazwa><sln:miejscRodzaj>Wieś</sln:miejscRodzaj><sln:powIIPId>adb95dd1-f39a-46c3-a2ee-c5dfb69b1d25</sln:powIIPId><sln:powIIPPn>PL.PZGIK.200</sln:powIIPPn><sln:powIIPWersja>2012-09-27T07:52:00+02:00</sln:powIIPWersja><sln:powIdTeryt>1214</sln:powIdTeryt><sln:powNazwa>proszowicki</sln:powNazwa><sln:waznyOd>2015-12-23T00:00:00+01:00</sln:waznyOd><sln:wojIIPId>dd2e3c64-f861-47cf-a3a3-e7751f272b2f</sln:wojIIPId><sln:wojIIPPn>PL.PZGIK.200</sln:wojIIPPn><sln:wojIIPWersja>2017-10-10T00:00:00+02:00</sln:wojIIPWersja><sln:wojIdTeryt>12</sln:wojIdTeryt><sln:wojNazwa>małopolskie</sln:wojNazwa></sln:miejscowosc><sln:miejscowosc><sln:cyklZyciaOd>2017-04-21T00:00:00+02:00</sln:cyklZyciaOd><sln:gmIIPId>fef90d5f-eb23-4381-bcde-f50bc3f1cf0f</sln:gmIIPId><sln:gmIIPPn>PL.PZGIK.200</sln:gmIIPPn><sln:gmIIPWersja>2012-09-26T22:11:56+02:00</sln:gmIIPWersja><sln:gmIdTeryt>1214012</sln:gmIdTeryt><sln:gmNazwa>Koniusza</sln:gmNazwa><sln:miejscIIPId>055d22b1-b7b2-401f-b9e8-b9d89a55e466</sln:miejscIIPId><sln:miejscIIPPn>PL.PZGIK.200</sln:miejscIIPPn><sln:miejscIIPWersja>2017-04-21T14:09:35+02:00</sln:miejscIIPWersja><sln:miejscIdTeryt>0322910</sln:miejscIdTeryt><sln:miejscNazwa>Dalewice</sln:miejscNazwa><sln:miejscRodzaj>Wieś</sln:miejscRodzaj><sln:powIIPId>adb95dd1-f39a-46c3-a2ee-c5dfb69b1d25</sln:powIIPId><sln:powIIPPn>PL.PZGIK.200</sln:powIIPPn><sln:powIIPWersja>2012-09-27T07:52:00+02:00</sln:powIIPWersja><sln:powIdTeryt>1214</sln:powIdTeryt><sln:powNazwa>proszowicki</sln:powNazwa><sln:waznyOd>2015-12-23T00:00:00+01:00</sln:waznyOd><sln:wojIIPId>dd2e3c64-f861-47cf-a3a3-e7751f272b2f</sln:wojIIPId><sln:wojIIPPn>PL.PZGIK.200</sln:wojIIPPn><sln:wojIIPWersja>2017-10-10T00:00:00+02:00</sln:wojIIPWersja><sln:wojIdTeryt>12</sln:wojIdTeryt><sln:wojNazwa>małopolskie</sln:wojNazwa></sln:miejscowosc><sln:miejscowosc><sln:cyklZyciaOd>2017-04-21T00:00:00+02:00</sln:cyklZyciaOd><sln:gmIIPId>fef90d5f-eb23-4381-bcde-f50bc3f1cf0f</sln:gmIIPId><sln:gmIIPPn>PL.PZGIK.200</sln:gmIIPPn><sln:gmIIPWersja>2012-09-26T22:11:56+02:00</sln:gmIIPWersja><sln:gmIdTeryt>1214012</sln:gmIdTeryt><sln:gmNazwa>Koniusza</sln:gmNazwa><sln:miejscIIPId>98b569d2-846c-4f5b-8468-823db0ce3c9c</sln:miejscIIPId><sln:miejscIIPPn>PL.PZGIK.200</sln:miejscIIPPn><sln:miejscIIPWersja>2017-04-21T14:09:36+02:00</sln:miejscIIPWersja><sln:miejscIdTeryt>0322956</sln:miejscIdTeryt><sln:miejscNazwa>Glew</sln:miejscNazwa><sln:miejscRodzaj>Wieś</sln:miejscRodzaj><sln:powIIPId>adb95dd1-f39a-46c3-a2ee-c5dfb69b1d25</sln:powIIPId><sln:powIIPPn>PL.PZGIK.200</sln:powIIPPn><sln:powIIPWersja>2012-09-27T07:52:00+02:00</sln:powIIPWersja><sln:powIdTeryt>1214</sln:powIdTeryt><sln:powNazwa>proszowicki</sln:powNazwa><sln:waznyOd>2015-12-23T00:00:00+01:00</sln:waznyOd><sln:wojIIPId>dd2e3c64-f861-47cf-a3a3-e7751f272b2f</sln:wojIIPId><sln:wojIIPPn>PL.PZGIK.200</sln:wojIIPPn><sln:wojIIPWersja>2017-10-10T00:00:00+02:00</sln:wojIIPWersja><sln:wojIdTeryt>12</sln:wojIdTeryt><sln:wojNazwa>małopolskie</sln:wojNazwa></sln:miejscowosc><sln:miejscowosc><sln:cyklZyciaOd>2017-04-21T00:00:00+02:00</sln:cyklZyciaOd><sln:gmIIPId>fef90d5f-eb23-4381-bcde-f50bc3f1cf0f</sln:gmIIPId><sln:gmIIPPn>PL.PZGIK.200</sln:gmIIPPn><sln:gmIIPWersja>2012-09-26T22:11:56+02:00</sln:gmIIPWersja><sln:gmIdTeryt>1214012</sln:gmIdTeryt><sln:gmNazwa>Koniusza</sln:gmNazwa><sln:miejscIIPId>4af400ce-b522-4267-a92a-b9bb3947c9dd</sln:miejscIIPId><sln:miejscIIPPn>PL.PZGIK.200</sln:miejscIIPPn><sln:miejscIIPWersja>2017-04-21T14:09:36+02:00</sln:miejscIIPWersja><sln:miejscIdTeryt>0322991</sln:miejscIdTeryt><sln:miejscNazwa>Glewiec</sln:miejscNazwa><sln:miejscRodzaj>Wieś</sln:miejscRodzaj><sln:powIIPId>adb95dd1-f39a-46c3-a2ee-c5dfb69b1d25</sln:powIIPId><sln:powIIPPn>PL.PZGIK.200</sln:powIIPPn><sln:powIIPWersja>2012-09-27T07:52:00+02:00</sln:powIIPWersja><sln:powIdTeryt>1214</sln:powIdTeryt><sln:powNazwa>proszowicki</sln:powNazwa><sln:waznyOd>2015-12-23T00:00:00+01:00</sln:waznyOd><sln:wojIIPId>dd2e3c64-f861-47cf-a3a3-e7751f272b2f</sln:wojIIPId><sln:wojIIPPn>PL.PZGIK.200</sln:wojIIPPn><sln:wojIIPWersja>2017-10-10T00:00:00+02:00</sln:wojIIPWersja><sln:wojIdTeryt>12</sln:wojIdTeryt><sln:wojNazwa>małopolskie</sln:wojNazwa></sln:miejscowosc><sln:miejscowosc><sln:cyklZyciaOd>2017-04-21T00:00:00+02:00</sln:cyklZyciaOd><sln:gmIIPId>fef90d5f-eb23-4381-bcde-f50bc3f1cf0f</sln:gmIIPId><sln:gmIIPPn>PL.PZGIK.200</sln:gmIIPPn><sln:gmIIPWersja>2012-09-26T22:11:56+02:00</sln:gmIIPWersja><sln:gmIdTeryt>1214012</sln:gmIdTeryt><sln:gmNazwa>Koniusza</sln:gmNazwa><sln:miejscIIPId>9d4aabfe-b7d3-4e8e-8cf1-f7432ebfa6ec</sln:miejscIIPId><sln:miejscIIPPn>PL.PZGIK.200</sln:miejscIIPPn><sln:miejscIIPWersja>2017-04-21T14:09:36+02:00</sln:miejscIIPWersja><sln:miejscIdTeryt>0323039</sln:miejscIdTeryt><sln:miejscNazwa>Gnatowice</sln:miejscNazwa><sln:miejscRodzaj>Wieś</sln:miejscRodzaj><sln:powIIPId>adb95dd1-f39a-46c3-a2ee-c5dfb69b1d25</sln:powIIPId><sln:powIIPPn>PL.PZGIK.200</sln:powIIPPn><sln:powIIPWersja>2012-09-27T07:52:00+02:00</sln:powIIPWersja><sln:powIdTeryt>1214</sln:powIdTeryt><sln:powNazwa>proszowicki</sln:powNazwa><sln:waznyOd>2015-12-23T00:00:00+01:00</sln:waznyOd><sln:wojIIPId>dd2e3c64-f861-47cf-a3a3-e7751f272b2f</sln:wojIIPId><sln:wojIIPPn>PL.PZGIK.200</sln:wojIIPPn><sln:wojIIPWersja>2017-10-10T00:00:00+02:00</sln:wojIIPWersja><sln:wojIdTeryt>12</sln:wojIdTeryt><sln:wojNazwa>małopolskie</sln:wojNazwa></sln:miejscowosc><sln:miejscowosc><sln:cyklZyciaOd>2017-04-21T00:00:00+02:00</sln:cyklZyciaOd><sln:gmIIPId>fef90d5f-eb23-4381-bcde-f50bc3f1cf0f</sln:gmIIPId><sln:gmIIPPn>PL.PZGIK.200</sln:gmIIPPn><sln:gmIIPWersja>2012-09-26T22:11:56+02:00</sln:gmIIPWersja><sln:gmIdTeryt>1214012</sln:gmIdTeryt><sln:gmNazwa>Koniusza</sln:gmNazwa><sln:miejscIIPId>c7d929b2-32f2-4a95-8389-2c9a8713baf4</sln:miejscIIPId><sln:miejscIIPPn>PL.PZGIK.200</sln:miejscIIPPn><sln:miejscIIPWersja>2017-04-21T14:09:36+02:00</sln:miejscIIPWersja><sln:miejscIdTeryt>0323080</sln:miejscIdTeryt><sln:miejscNazwa>Górka Jaklińska</sln:miejscNazwa><sln:miejscRodzaj>Wieś</sln:miejscRodzaj><sln:powIIPId>adb95dd1-f39a-46c3-a2ee-c5dfb69b1d25</sln:powIIPId><sln:powIIPPn>PL.PZGIK.200</sln:powIIPPn><sln:powIIPWersja>2012-09-27T07:52:00+02:00</sln:powIIPWersja><sln:powIdTeryt>1214</sln:powIdTeryt><sln:powNazwa>proszowicki</sln:powNazwa><sln:waznyOd>2015-12-23T00:00:00+01:00</sln:waznyOd><sln:wojIIPId>dd2e3c64-f861-47cf-a3a3-e7751f272b2f</sln:wojIIPId><sln:wojIIPPn>PL.PZGIK.200</sln:wojIIPPn><sln:wojIIPWersja>2017-10-10T00:00:00+02:00</sln:wojIIPWersja><sln:wojIdTeryt>12</sln:wojIdTeryt><sln:wojNazwa>małopolskie</sln:wojNazwa></sln:miejscowosc><sln:miejscowosc><sln:cyklZyciaOd>2017-04-21T00:00:00+02:00</sln:cyklZyciaOd><sln:gmIIPId>fef90d5f-eb23-4381-bcde-f50bc3f1cf0f</sln:gmIIPId><sln:gmIIPPn>PL.PZGIK.200</sln:gmIIPPn><sln:gmIIPWersja>2012-09-26T22:11:56+02:00</sln:gmIIPWersja><sln:gmIdTeryt>1214012</sln:gmIdTeryt><sln:gmNazwa>Koniusza</sln:gmNazwa><sln:miejscIIPId>22be0f2f-8380-4319-8ab0-e98acd89be8b</sln:miejscIIPId><sln:miejscIIPPn>PL.PZGIK.200</sln:miejscIIPPn><sln:miejscIIPWersja>2017-04-21T14:09:36+02:00</sln:miejscIIPWersja><sln:miejscIdTeryt>0323140</sln:miejscIdTeryt><sln:miejscNazwa>Karwin</sln:miejscNazwa><sln:miejscRodzaj>Wieś</sln:miejscRodzaj><sln:powIIPId>adb95dd1-f39a-46c3-a2ee-c5dfb69b1d25</sln:powIIPId><sln:powIIPPn>PL.PZGIK.200</sln:powIIPPn><sln:powIIPWersja>2012-09-27T07:52:00+02:00</sln:powIIPWersja><sln:powIdTeryt>1214</sln:powIdTeryt><sln:powNazwa>proszowicki</sln:powNazwa><sln:waznyOd>2015-12-23T00:00:00+01:00</sln:waznyOd><sln:wojIIPId>dd2e3c64-f861-47cf-a3a3-e7751f272b2f</sln:wojIIPId><sln:wojIIPPn>PL.PZGIK.200</sln:wojIIPPn><sln:wojIIPWersja>2017-10-10T00:00:00+02:00</sln:wojIIPWersja><sln:wojIdTeryt>12</sln:wojIdTeryt><sln:wojNazwa>małopolskie</sln:wojNazwa></sln:miejscowosc><sln:miejscowosc><sln:cyklZyciaOd>2017-04-21T00:00:00+02:00</sln:cyklZyciaOd><sln:gmIIPId>fef90d5f-eb23-4381-bcde-f50bc3f1cf0f</sln:gmIIPId><sln:gmIIPPn>PL.PZGIK.200</sln:gmIIPPn><sln:gmIIPWersja>2012-09-26T22:11:56+02:00</sln:gmIIPWersja><sln:gmIdTeryt>1214012</sln:gmIdTeryt><sln:gmNazwa>Koniusza</sln:gmNazwa><sln:miejscIIPId>7437d4dc-4801-4ae8-ad06-0699280e5669</sln:miejscIIPId><sln:miejscIIPPn>PL.PZGIK.200</sln:miejscIIPPn><sln:miejscIIPWersja>2017-04-21T14:09:36+02:00</sln:miejscIIPWersja><sln:miejscIdTeryt>0323230</sln:miejscIdTeryt><sln:miejscNazwa>Koniusza</sln:miejscNazwa><sln:miejscRodzaj>Wieś</sln:miejscRodzaj><sln:powIIPId>adb95dd1-f39a-46c3-a2ee-c5dfb69b1d25</sln:powIIPId><sln:powIIPPn>PL.PZGIK.200</sln:powIIPPn><sln:powIIPWersja>2012-09-27T07:52:00+02:00</sln:powIIPWersja><sln:powIdTeryt>1214</sln:powIdTeryt><sln:powNazwa>proszowicki</sln:powNazwa><sln:waznyOd>2015-12-23T00:00:00+01:00</sln:waznyOd><sln:wojIIPId>dd2e3c64-f861-47cf-a3a3-e7751f272b2f</sln:wojIIPId><sln:wojIIPPn>PL.PZGIK.200</sln:wojIIPPn><sln:wojIIPWersja>2017-10-10T00:00:00+02:00</sln:wojIIPWersja><sln:wojIdTeryt>12</sln:wojIdTeryt><sln:wojNazwa>małopolskie</sln:wojNazwa></sln:miejscowosc><sln:miejscowosc><sln:cyklZyciaOd>2017-04-21T00:00:00+02:00</sln:cyklZyciaOd><sln:gmIIPId>fef90d5f-eb23-4381-bcde-f50bc3f1cf0f</sln:gmIIPId><sln:gmIIPPn>PL.PZGIK.200</sln:gmIIPPn><sln:gmIIPWersja>2012-09-26T22:11:56+02:00</sln:gmIIPWersja><sln:gmIdTeryt>1214012</sln:gmIdTeryt><sln:gmNazwa>Koniusza</sln:gmNazwa><sln:miejscIIPId>8c66d8d0-67ed-483c-a628-b107eabcc8bc</sln:miejscIIPId><sln:miejscIIPPn>PL.PZGIK.200</sln:miejscIIPPn><sln:miejscIIPWersja>2017-04-21T14:09:36+02:00</sln:miejscIIPWersja><sln:miejscIdTeryt>0323269</sln:miejscIdTeryt><sln:miejscNazwa>Łyszkowice</sln:miejscNazwa><sln:miejscRodzaj>Wieś</sln:miejscRodzaj><sln:powIIPId>adb95dd1-f39a-46c3-a2ee-c5dfb69b1d25</sln:powIIPId><sln:powIIPPn>PL.PZGIK.200</sln:powIIPPn><sln:powIIPWersja>2012-09-27T07:52:00+02:00</sln:powIIPWersja><sln:powIdTeryt>1214</sln:powIdTeryt><sln:powNazwa>proszowicki</sln:powNazwa><sln:waznyOd>2015-12-23T00:00:00+01:00</sln:waznyOd><sln:wojIIPId>dd2e3c64-f861-47cf-a3a3-e7751f272b2f</sln:wojIIPId><sln:wojIIPPn>PL.PZGIK.200</sln:wojIIPPn><sln:wojIIPWersja>2017-10-10T00:00:00+02:00</sln:wojIIPWersja><sln:wojIdTeryt>12</sln:wojIdTeryt><sln:wojNazwa>małopolskie</sln:wojNazwa></sln:miejscowosc><sln:miejscowosc><sln:cyklZyciaOd>2017-04-21T00:00:00+02:00</sln:cyklZyciaOd><sln:gmIIPId>fef90d5f-eb23-4381-bcde-f50bc3f1cf0f</sln:gmIIPId><sln:gmIIPPn>PL.PZGIK.200</sln:gmIIPPn><sln:gmIIPWersja>2012-09-26T22:11:56+02:00</sln:gmIIPWersja><sln:gmIdTeryt>1214012</sln:gmIdTeryt><sln:gmNazwa>Koniusza</sln:gmNazwa><sln:miejscIIPId>57bf956d-65c6-498e-ac7c-1b5775d28870</sln:miejscIIPId><sln:miejscIIPPn>PL.PZGIK.200</sln:miejscIIPPn><sln:miejscIIPWersja>2017-04-21T14:09:36+02:00</sln:miejscIIPWersja><sln:miejscIdTeryt>0323358</sln:miejscIdTeryt><sln:miejscNazwa>Muniaczkowice</sln:miejscNazwa><sln:miejscRodzaj>Wieś</sln:miejscRodzaj><sln:powIIPId>adb95dd1-f39a-46c3-a2ee-c5dfb69b1d25</sln:powIIPId><sln:powIIPPn>PL.PZGIK.200</sln:powIIPPn><sln:powIIPWersja>2012-09-27T07:52:00+02:00</sln:powIIPWersja><sln:powIdTeryt>1214</sln:powIdTeryt><sln:powNazwa>proszowicki</sln:powNazwa><sln:waznyOd>2015-12-23T00:00:00+01:00</sln:waznyOd><sln:wojIIPId>dd2e3c64-f861-47cf-a3a3-e7751f272b2f</sln:wojIIPId><sln:wojIIPPn>PL.PZGIK.200</sln:wojIIPPn><sln:wojIIPWersja>2017-10-10T00:00:00+02:00</sln:wojIIPWersja><sln:wojIdTeryt>12</sln:wojIdTeryt><sln:wojNazwa>małopolskie</sln:wojNazwa></sln:miejscowosc><sln:miejscowosc><sln:cyklZyciaOd>2017-04-21T00:00:00+02:00</sln:cyklZyciaOd><sln:gmIIPId>fef90d5f-eb23-4381-bcde-f50bc3f1cf0f</sln:gmIIPId><sln:gmIIPPn>PL.PZGIK.200</sln:gmIIPPn><sln:gmIIPWersja>2012-09-26T22:11:56+02:00</sln:gmIIPWersja><sln:gmIdTeryt>1214012</sln:gmIdTeryt><sln:gmNazwa>Koniusza</sln:gmNazwa><sln:miejscIIPId>280f4319-a658-41e4-a26c-ae287468340c</sln:miejscIIPId><sln:miejscIIPPn>PL.PZGIK.200</sln:miejscIIPPn><sln:miejscIIPWersja>2017-04-21T14:09:36+02:00</sln:miejscIIPWersja><sln:miejscIdTeryt>0323393</sln:miejscIdTeryt><sln:miejscNazwa>Niegardów</sln:miejscNazwa><sln:miejscRodzaj>Wieś</sln:miejscRodzaj><sln:powIIPId>adb95dd1-f39a-46c3-a2ee-c5dfb69b1d25</sln:powIIPId><sln:powIIPPn>PL.PZGIK.200</sln:powIIPPn><sln:powIIPWersja>2012-09-27T07:52:00+02:00</sln:powIIPWersja><sln:powIdTeryt>1214</sln:powIdTeryt><sln:powNazwa>proszowicki</sln:powNazwa><sln:waznyOd>2015-12-23T00:00:00+01:00</sln:waznyOd><sln:wojIIPId>dd2e3c64-f861-47cf-a3a3-e7751f272b2f</sln:wojIIPId><sln:wojIIPPn>PL.PZGIK.200</sln:wojIIPPn><sln:wojIIPWersja>2017-10-10T00:00:00+02:00</sln:wojIIPWersja><sln:wojIdTeryt>12</sln:wojIdTeryt><sln:wojNazwa>małopolskie</sln:wojNazwa></sln:miejscowosc><sln:miejscowosc><sln:cyklZyciaOd>2017-04-21T00:00:00+02:00</sln:cyklZyciaOd><sln:gmIIPId>fef90d5f-eb23-4381-bcde-f50bc3f1cf0f</sln:gmIIPId><sln:gmIIPPn>PL.PZGIK.200</sln:gmIIPPn><sln:gmIIPWersja>2012-09-26T22:11:56+02:00</sln:gmIIPWersja><sln:gmIdTeryt>1214012</sln:gmIdTeryt><sln:gmNazwa>Koniusza</sln:gmNazwa><sln:miejscIIPId>ad6872c8-5a90-45e1-b091-cf9d1537b928</sln:miejscIIPId><sln:miejscIIPPn>PL.PZGIK.200</sln:miejscIIPPn><sln:miejscIIPWersja>2017-04-21T14:09:36+02:00</sln:miejscIIPWersja><sln:miejscIdTeryt>0323453</sln:miejscIdTeryt><sln:miejscNazwa>Niegardów-Kolonia</sln:miejscNazwa><sln:miejscRodzaj>Wieś</sln:miejscRodzaj><sln:powIIPId>adb95dd1-f39a-46c3-a2ee-c5dfb69b1d25</sln:powIIPId><sln:powIIPPn>PL.PZGIK.200</sln:powIIPPn><sln:powIIPWersja>2012-09-27T07:52:00+02:00</sln:powIIPWersja><sln:powIdTeryt>1214</sln:powIdTeryt><sln:powNazwa>proszowicki</sln:powNazwa><sln:waznyOd>2015-12-23T00:00:00+01:00</sln:waznyOd><sln:wojIIPId>dd2e3c64-f861-47cf-a3a3-e7751f272b2f</sln:wojIIPId><sln:wojIIPPn>PL.PZGIK.200</sln:wojIIPPn><sln:wojIIPWersja>2017-10-10T00:00:00+02:00</sln:wojIIPWersja><sln:wojIdTeryt>12</sln:wojIdTeryt><sln:wojNazwa>małopolskie</sln:wojNazwa></sln:miejscowosc><sln:miejscowosc><sln:cyklZyciaOd>2017-04-21T00:00:00+02:00</sln:cyklZyciaOd><sln:gmIIPId>fef90d5f-eb23-4381-bcde-f50bc3f1cf0f</sln:gmIIPId><sln:gmIIPPn>PL.PZGIK.200</sln:gmIIPPn><sln:gmIIPWersja>2012-09-26T22:11:56+02:00</sln:gmIIPWersja><sln:gmIdTeryt>1214012</sln:gmIdTeryt><sln:gmNazwa>Koniusza</sln:gmNazwa><sln:miejscIIPId>fca87a69-3d24-49ca-81fe-295912442921</sln:miejscIIPId><sln:miejscIIPPn>PL.PZGIK.200</sln:miejscIIPPn><sln:miejscIIPWersja>2017-04-21T14:09:36+02:00</sln:miejscIIPWersja><sln:miejscIdTeryt>0323499</sln:miejscIdTeryt><sln:miejscNazwa>Piotrkowice Małe</sln:miejscNazwa><sln:miejscRodzaj>Wieś</sln:miejscRodzaj><sln:powIIPId>adb95dd1-f39a-46c3-a2ee-c5dfb69b1d25</sln:powIIPId><sln:powIIPPn>PL.PZGIK.200</sln:powIIPPn><sln:powIIPWersja>2012-09-27T07:52:00+02:00</sln:powIIPWersja><sln:powIdTeryt>1214</sln:powIdTeryt><sln:powNazwa>proszowicki</sln:powNazwa><sln:waznyOd>2015-12-23T00:00:00+01:00</sln:waznyOd><sln:wojIIPId>dd2e3c64-f861-47cf-a3a3-e7751f272b2f</sln:wojIIPId><sln:wojIIPPn>PL.PZGIK.200</sln:wojIIPPn><sln:wojIIPWersja>2017-10-10T00:00:00+02:00</sln:wojIIPWersja><sln:wojIdTeryt>12</sln:wojIdTeryt><sln:wojNazwa>małopolskie</sln:wojNazwa></sln:miejscowosc><sln:miejscowosc><sln:cyklZyciaOd>2017-04-21T00:00:00+02:00</sln:cyklZyciaOd><sln:gmIIPId>fef90d5f-eb23-4381-bcde-f50bc3f1cf0f</sln:gmIIPId><sln:gmIIPPn>PL.PZGIK.200</sln:gmIIPPn><sln:gmIIPWersja>2012-09-26T22:11:56+02:00</sln:gmIIPWersja><sln:gmIdTeryt>1214012</sln:gmIdTeryt><sln:gmNazwa>Koniusza</sln:gmNazwa><sln:miejscIIPId>2f3969f1-3c69-452a-abfd-35a093d63a36</sln:miejscIIPId><sln:miejscIIPPn>PL.PZGIK.200</sln:miejscIIPPn><sln:miejscIIPWersja>2017-04-21T14:09:37+02:00</sln:miejscIIPWersja><sln:miejscIdTeryt>0323536</sln:miejscIdTeryt><sln:miejscNazwa>Piotrkowice Wielkie</sln:miejscNazwa><sln:miejscRodzaj>Wieś</sln:miejscRodzaj><sln:powIIPId>adb95dd1-f39a-46c3-a2ee-c5dfb69b1d25</sln:powIIPId><sln:powIIPPn>PL.PZGIK.200</sln:powIIPPn><sln:powIIPWersja>2012-09-27T07:52:00+02:00</sln:powIIPWersja><sln:powIdTeryt>1214</sln:powIdTeryt><sln:powNazwa>proszowicki</sln:powNazwa><sln:waznyOd>2015-12-23T00:00:00+01:00</sln:waznyOd><sln:wojIIPId>dd2e3c64-f861-47cf-a3a3-e7751f272b2f</sln:wojIIPId><sln:wojIIPPn>PL.PZGIK.200</sln:wojIIPPn><sln:wojIIPWersja>2017-10-10T00:00:00+02:00</sln:wojIIPWersja><sln:wojIdTeryt>12</sln:wojIdTeryt><sln:wojNazwa>małopolskie</sln:wojNazwa></sln:miejscowosc><sln:miejscowosc><sln:cyklZyciaOd>2017-04-21T00:00:00+02:00</sln:cyklZyciaOd><sln:gmIIPId>fef90d5f-eb23-4381-bcde-f50bc3f1cf0f</sln:gmIIPId><sln:gmIIPPn>PL.PZGIK.200</sln:gmIIPPn><sln:gmIIPWersja>2012-09-26T22:11:56+02:00</sln:gmIIPWersja><sln:gmIdTeryt>1214012</sln:gmIdTeryt><sln:gmNazwa>Koniusza</sln:gmNazwa><sln:miejscIIPId>96c86507-0e67-499a-aa30-f135e5d206f7</sln:miejscIIPId><sln:miejscIIPPn>PL.PZGIK.200</sln:miejscIIPPn><sln:miejscIIPWersja>2017-04-21T14:09:37+02:00</sln:miejscIIPWersja><sln:miejscIdTeryt>0323588</sln:miejscIdTeryt><sln:miejscNazwa>Polekarcice</sln:miejscNazwa><sln:miejscRodzaj>Wieś</sln:miejscRodzaj><sln:powIIPId>adb95dd1-f39a-46c3-a2ee-c5dfb69b1d25</sln:powIIPId><sln:powIIPPn>PL.PZGIK.200</sln:powIIPPn><sln:powIIPWersja>2012-09-27T07:52:00+02:00</sln:powIIPWersja><sln:powIdTeryt>1214</sln:powIdTeryt><sln:powNazwa>proszowicki</sln:powNazwa><sln:waznyOd>2015-12-23T00:00:00+01:00</sln:waznyOd><sln:wojIIPId>dd2e3c64-f861-47cf-a3a3-e7751f272b2f</sln:wojIIPId><sln:wojIIPPn>PL.PZGIK.200</sln:wojIIPPn><sln:wojIIPWersja>2017-10-10T00:00:00+02:00</sln:wojIIPWersja><sln:wojIdTeryt>12</sln:wojIdTeryt><sln:wojNazwa>małopolskie</sln:wojNazwa></sln:miejscowosc><sln:miejscowosc><sln:cyklZyciaOd>2017-04-21T00:00:00+02:00</sln:cyklZyciaOd><sln:gmIIPId>fef90d5f-eb23-4381-bcde-f50bc3f1cf0f</sln:gmIIPId><sln:gmIIPPn>PL.PZGIK.200</sln:gmIIPPn><sln:gmIIPWersja>2012-09-26T22:11:56+02:00</sln:gmIIPWersja><sln:gmIdTeryt>1214012</sln:gmIdTeryt><sln:gmNazwa>Koniusza</sln:gmNazwa><sln:miejscIIPId>d5d9502b-b160-4f6c-a1d6-9c46e8bac38a</sln:miejscIIPId><sln:miejscIIPPn>PL.PZGIK.200</sln:miejscIIPPn><sln:miejscIIPWersja>2017-04-21T14:09:37+02:00</sln:miejscIIPWersja><sln:miejscIdTeryt>0323625</sln:miejscIdTeryt><sln:miejscNazwa>Posądza</sln:miejscNazwa><sln:miejscRodzaj>Wieś</sln:miejscRodzaj><sln:powIIPId>adb95dd1-f39a-46c3-a2ee-c5dfb69b1d25</sln:powIIPId><sln:powIIPPn>PL.PZGIK.200</sln:powIIPPn><sln:powIIPWersja>2012-09-27T07:52:00+02:00</sln:powIIPWersja><sln:powIdTeryt>1214</sln:powIdTeryt><sln:powNazwa>proszowicki</sln:powNazwa><sln:waznyOd>2015-12-23T00:00:00+01:00</sln:waznyOd><sln:wojIIPId>dd2e3c64-f861-47cf-a3a3-e7751f272b2f</sln:wojIIPId><sln:wojIIPPn>PL.PZGIK.200</sln:wojIIPPn><sln:wojIIPWersja>2017-10-10T00:00:00+02:00</sln:wojIIPWersja><sln:wojIdTeryt>12</sln:wojIdTeryt><sln:wojNazwa>małopolskie</sln:wojNazwa></sln:miejscowosc><sln:miejscowosc><sln:cyklZyciaOd>2017-04-21T00:00:00+02:00</sln:cyklZyciaOd><sln:gmIIPId>fef90d5f-eb23-4381-bcde-f50bc3f1cf0f</sln:gmIIPId><sln:gmIIPPn>PL.PZGIK.200</sln:gmIIPPn><sln:gmIIPWersja>2012-09-26T22:11:56+02:00</sln:gmIIPWersja><sln:gmIdTeryt>1214012</sln:gmIdTeryt><sln:gmNazwa>Koniusza</sln:gmNazwa><sln:miejscIIPId>952ae64d-d192-4205-bff8-eddc162cfe36</sln:miejscIIPId><sln:miejscIIPPn>PL.PZGIK.200</sln:miejscIIPPn><sln:miejscIIPWersja>2017-04-21T14:09:37+02:00</sln:miejscIIPWersja><sln:miejscIdTeryt>0323677</sln:miejscIdTeryt><sln:miejscNazwa>Przesławice</sln:miejscNazwa><sln:miejscRodzaj>Wieś</sln:miejscRodzaj><sln:powIIPId>adb95dd1-f39a-46c3-a2ee-c5dfb69b1d25</sln:powIIPId><sln:powIIPPn>PL.PZGIK.200</sln:powIIPPn><sln:powIIPWersja>2012-09-27T07:52:00+02:00</sln:powIIPWersja><sln:powIdTeryt>1214</sln:powIdTeryt><sln:powNazwa>proszowicki</sln:powNazwa><sln:waznyOd>2015-12-23T00:00:00+01:00</sln:waznyOd><sln:wojIIPId>dd2e3c64-f861-47cf-a3a3-e7751f272b2f</sln:wojIIPId><sln:wojIIPPn>PL.PZGIK.200</sln:wojIIPPn><sln:wojIIPWersja>2017-10-10T00:00:00+02:00</sln:wojIIPWersja><sln:wojIdTeryt>12</sln:wojIdTeryt><sln:wojNazwa>małopolskie</sln:wojNazwa></sln:miejscowosc><sln:miejscowosc><sln:cyklZyciaOd>2017-04-21T00:00:00+02:00</sln:cyklZyciaOd><sln:gmIIPId>fef90d5f-eb23-4381-bcde-f50bc3f1cf0f</sln:gmIIPId><sln:gmIIPPn>PL.PZGIK.200</sln:gmIIPPn><sln:gmIIPWersja>2012-09-26T22:11:56+02:00</sln:gmIIPWersja><sln:gmIdTeryt>1214012</sln:gmIdTeryt><sln:gmNazwa>Koniusza</sln:gmNazwa><sln:miejscIIPId>f1a947fb-2d2e-4a24-ba27-95180506fec3</sln:miejscIIPId><sln:miejscIIPPn>PL.PZGIK.200</sln:miejscIIPPn><sln:miejscIIPWersja>2017-04-21T14:09:37+02:00</sln:miejscIIPWersja><sln:miejscIdTeryt>0323720</sln:miejscIdTeryt><sln:miejscNazwa>Rzędowice</sln:miejscNazwa><sln:miejscRodzaj>Wieś</sln:miejscRodzaj><sln:powIIPId>adb95dd1-f39a-46c3-a2ee-c5dfb69b1d25</sln:powIIPId><sln:powIIPPn>PL.PZGIK.200</sln:powIIPPn><sln:powIIPWersja>2012-09-27T07:52:00+02:00</sln:powIIPWersja><sln:powIdTeryt>1214</sln:powIdTeryt><sln:powNazwa>proszowicki</sln:powNazwa><sln:waznyOd>2015-12-23T00:00:00+01:00</sln:waznyOd><sln:wojIIPId>dd2e3c64-f861-47cf-a3a3-e7751f272b2f</sln:wojIIPId><sln:wojIIPPn>PL.PZGIK.200</sln:wojIIPPn><sln:wojIIPWersja>2017-10-10T00:00:00+02:00</sln:wojIIPWersja><sln:wojIdTeryt>12</sln:wojIdTeryt><sln:wojNazwa>małopolskie</sln:wojNazwa></sln:miejscowosc><sln:miejscowosc><sln:cyklZyciaOd>2017-04-21T00:00:00+02:00</sln:cyklZyciaOd><sln:gmIIPId>fef90d5f-eb23-4381-bcde-f50bc3f1cf0f</sln:gmIIPId><sln:gmIIPPn>PL.PZGIK.200</sln:gmIIPPn><sln:gmIIPWersja>2012-09-26T22:11:56+02:00</sln:gmIIPWersja><sln:gmIdTeryt>1214012</sln:gmIdTeryt><sln:gmNazwa>Koniusza</sln:gmNazwa><sln:miejscIIPId>c8e811af-e7ac-4939-8453-bfdb58faec51</sln:miejscIIPId><sln:miejscIIPPn>PL.PZGIK.200</sln:miejscIIPPn><sln:miejscIIPWersja>2017-04-21T14:09:37+02:00</sln:miejscIIPWersja><sln:miejscIdTeryt>0323743</sln:miejscIdTeryt><sln:miejscNazwa>Siedliska</sln:miejscNazwa><sln:miejscRodzaj>Wieś</sln:miejscRodzaj><sln:powIIPId>adb95dd1-f39a-46c3-a2ee-c5dfb69b1d25</sln:powIIPId><sln:powIIPPn>PL.PZGIK.200</sln:powIIPPn><sln:powIIPWersja>2012-09-27T07:52:00+02:00</sln:powIIPWersja><sln:powIdTeryt>1214</sln:powIdTeryt><sln:powNazwa>proszowicki</sln:powNazwa><sln:waznyOd>2015-12-23T00:00:00+01:00</sln:waznyOd><sln:wojIIPId>dd2e3c64-f861-47cf-a3a3-e7751f272b2f</sln:wojIIPId><sln:wojIIPPn>PL.PZGIK.200</sln:wojIIPPn><sln:wojIIPWersja>2017-10-10T00:00:00+02:00</sln:wojIIPWersja><sln:wojIdTeryt>12</sln:wojIdTeryt><sln:wojNazwa>małopolskie</sln:wojNazwa></sln:miejscowosc><sln:miejscowosc><sln:cyklZyciaOd>2017-04-21T00:00:00+02:00</sln:cyklZyciaOd><sln:gmIIPId>fef90d5f-eb23-4381-bcde-f50bc3f1cf0f</sln:gmIIPId><sln:gmIIPPn>PL.PZGIK.200</sln:gmIIPPn><sln:gmIIPWersja>2012-09-26T22:11:56+02:00</sln:gmIIPWersja><sln:gmIdTeryt>1214012</sln:gmIdTeryt><sln:gmNazwa>Koniusza</sln:gmNazwa><sln:miejscIIPId>51615ecf-f3c8-44c9-b821-7f8d3ae23b3c</sln:miejscIIPId><sln:miejscIIPPn>PL.PZGIK.200</sln:miejscIIPPn><sln:miejscIIPWersja>2017-04-21T14:09:37+02:00</sln:miejscIIPWersja><sln:miejscIdTeryt>0323803</sln:miejscIdTeryt><sln:miejscNazwa>Szarbia</sln:miejscNazwa><sln:miejscRodzaj>Wieś</sln:miejscRodzaj><sln:powIIPId>adb95dd1-f39a-46c3-a2ee-c5dfb69b1d25</sln:powIIPId><sln:powIIPPn>PL.PZGIK.200</sln:powIIPPn><sln:powIIPWersja>2012-09-27T07:52:00+02:00</sln:powIIPWersja><sln:powIdTeryt>1214</sln:powIdTeryt><sln:powNazwa>proszowicki</sln:powNazwa><sln:waznyOd>2015-12-23T00:00:00+01:00</sln:waznyOd><sln:wojIIPId>dd2e3c64-f861-47cf-a3a3-e7751f272b2f</sln:wojIIPId><sln:wojIIPPn>PL.PZGIK.200</sln:wojIIPPn><sln:wojIIPWersja>2017-10-10T00:00:00+02:00</sln:wojIIPWersja><sln:wojIdTeryt>12</sln:wojIdTeryt><sln:wojNazwa>małopolskie</sln:wojNazwa></sln:miejscowosc><sln:miejscowosc><sln:cyklZyciaOd>2017-04-21T00:00:00+02:00</sln:cyklZyciaOd><sln:gmIIPId>fef90d5f-eb23-4381-bcde-f50bc3f1cf0f</sln:gmIIPId><sln:gmIIPPn>PL.PZGIK.200</sln:gmIIPPn><sln:gmIIPWersja>2012-09-26T22:11:56+02:00</sln:gmIIPWersja><sln:gmIdTeryt>1214012</sln:gmIdTeryt><sln:gmNazwa>Koniusza</sln:gmNazwa><sln:miejscIIPId>b8198fb9-3d11-400d-beed-af536f381cb2</sln:miejscIIPId><sln:miejscIIPPn>PL.PZGIK.200</sln:miejscIIPPn><sln:miejscIIPWersja>2017-04-21T14:09:37+02:00</sln:miejscIIPWersja><sln:miejscIdTeryt>0323832</sln:miejscIdTeryt><sln:miejscNazwa>Wąsów</sln:miejscNazwa><sln:miejscRodzaj>Wieś</sln:miejscRodzaj><sln:powIIPId>adb95dd1-f39a-46c3-a2ee-c5dfb69b1d25</sln:powIIPId><sln:powIIPPn>PL.PZGIK.200</sln:powIIPPn><sln:powIIPWersja>2012-09-27T07:52:00+02:00</sln:powIIPWersja><sln:powIdTeryt>1214</sln:powIdTeryt><sln:powNazwa>proszowicki</sln:powNazwa><sln:waznyOd>2015-12-23T00:00:00+01:00</sln:waznyOd><sln:wojIIPId>dd2e3c64-f861-47cf-a3a3-e7751f272b2f</sln:wojIIPId><sln:wojIIPPn>PL.PZGIK.200</sln:wojIIPPn><sln:wojIIPWersja>2017-10-10T00:00:00+02:00</sln:wojIIPWersja><sln:wojIdTeryt>12</sln:wojIdTeryt><sln:wojNazwa>małopolskie</sln:wojNazwa></sln:miejscowosc><sln:miejscowosc><sln:cyklZyciaOd>2017-04-21T00:00:00+02:00</sln:cyklZyciaOd><sln:gmIIPId>fef90d5f-eb23-4381-bcde-f50bc3f1cf0f</sln:gmIIPId><sln:gmIIPPn>PL.PZGIK.200</sln:gmIIPPn><sln:gmIIPWersja>2012-09-26T22:11:56+02:00</sln:gmIIPWersja><sln:gmIdTeryt>1214012</sln:gmIdTeryt><sln:gmNazwa>Koniusza</sln:gmNazwa><sln:miejscIIPId>5dd5f40e-ae15-4182-9600-086e57fdc881</sln:miejscIIPId><sln:miejscIIPPn>PL.PZGIK.200</sln:miejscIIPPn><sln:miejscIIPWersja>2017-04-21T14:09:37+02:00</sln:miejscIIPWersja><sln:miejscIdTeryt>0323878</sln:miejscIdTeryt><sln:miejscNazwa>Wierzbno</sln:miejscNazwa><sln:miejscRodzaj>Wieś</sln:miejscRodzaj><sln:powIIPId>adb95dd1-f39a-46c3-a2ee-c5dfb69b1d25</sln:powIIPId><sln:powIIPPn>PL.PZGIK.200</sln:powIIPPn><sln:powIIPWersja>2012-09-27T07:52:00+02:00</sln:powIIPWersja><sln:powIdTeryt>1214</sln:powIdTeryt><sln:powNazwa>proszowicki</sln:powNazwa><sln:waznyOd>2015-12-23T00:00:00+01:00</sln:waznyOd><sln:wojIIPId>dd2e3c64-f861-47cf-a3a3-e7751f272b2f</sln:wojIIPId><sln:wojIIPPn>PL.PZGIK.200</sln:wojIIPPn><sln:wojIIPWersja>2017-10-10T00:00:00+02:00</sln:wojIIPWersja><sln:wojIdTeryt>12</sln:wojIdTeryt><sln:wojNazwa>małopolskie</sln:wojNazwa></sln:miejscowosc><sln:miejscowosc><sln:cyklZyciaOd>2017-04-21T00:00:00+02:00</sln:cyklZyciaOd><sln:gmIIPId>fef90d5f-eb23-4381-bcde-f50bc3f1cf0f</sln:gmIIPId><sln:gmIIPPn>PL.PZGIK.200</sln:gmIIPPn><sln:gmIIPWersja>2012-09-26T22:11:56+02:00</sln:gmIIPWersja><sln:gmIdTeryt>1214012</sln:gmIdTeryt><sln:gmNazwa>Koniusza</sln:gmNazwa><sln:miejscIIPId>b8b45435-7978-4c2e-86c1-3b7a6ea23a9d</sln:miejscIIPId><sln:miejscIIPPn>PL.PZGIK.200</sln:miejscIIPPn><sln:miejscIIPWersja>2017-04-21T14:09:37+02:00</sln:miejscIIPWersja><sln:miejscIdTeryt>0323909</sln:miejscIdTeryt><sln:miejscNazwa>Wroniec</sln:miejscNazwa><sln:miejscRodzaj>Wieś</sln:miejscRodzaj><sln:powIIPId>adb95dd1-f39a-46c3-a2ee-c5dfb69b1d25</sln:powIIPId><sln:powIIPPn>PL.PZGIK.200</sln:powIIPPn><sln:powIIPWersja>2012-09-27T07:52:00+02:00</sln:powIIPWersja><sln:powIdTeryt>1214</sln:powIdTeryt><sln:powNazwa>proszowicki</sln:powNazwa><sln:waznyOd>2015-12-23T00:00:00+01:00</sln:waznyOd><sln:wojIIPId>dd2e3c64-f861-47cf-a3a3-e7751f272b2f</sln:wojIIPId><sln:wojIIPPn>PL.PZGIK.200</sln:wojIIPPn><sln:wojIIPWersja>2017-10-10T00:00:00+02:00</sln:wojIIPWersja><sln:wojIdTeryt>12</sln:wojIdTeryt><sln:wojNazwa>małopolskie</sln:wojNazwa></sln:miejscowosc><sln:miejscowosc><sln:cyklZyciaOd>2017-04-21T00:00:00+02:00</sln:cyklZyciaOd><sln:gmIIPId>fef90d5f-eb23-4381-bcde-f50bc3f1cf0f</sln:gmIIPId><sln:gmIIPPn>PL.PZGIK.200</sln:gmIIPPn><sln:gmIIPWersja>2012-09-26T22:11:56+02:00</sln:gmIIPWersja><sln:gmIdTeryt>1214012</sln:gmIdTeryt><sln:gmNazwa>Koniusza</sln:gmNazwa><sln:miejscIIPId>c74410ec-f236-4642-9544-6676ec61addb</sln:miejscIIPId><sln:miejscIIPPn>PL.PZGIK.200</sln:miejscIIPPn><sln:miejscIIPWersja>2017-04-21T14:09:37+02:00</sln:miejscIIPWersja><sln:miejscIdTeryt>0323944</sln:miejscIdTeryt><sln:miejscNazwa>Wronin</sln:miejscNazwa><sln:miejscRodzaj>Wieś</sln:miejscRodzaj><sln:powIIPId>adb95dd1-f39a-46c3-a2ee-c5dfb69b1d25</sln:powIIPId><sln:powIIPPn>PL.PZGIK.200</sln:powIIPPn><sln:powIIPWersja>2012-09-27T07:52:00+02:00</sln:powIIPWersja><sln:powIdTeryt>1214</sln:powIdTeryt><sln:powNazwa>proszowicki</sln:powNazwa><sln:waznyOd>2015-12-23T00:00:00+01:00</sln:waznyOd><sln:wojIIPId>dd2e3c64-f861-47cf-a3a3-e7751f272b2f</sln:wojIIPId><sln:wojIIPPn>PL.PZGIK.200</sln:wojIIPPn><sln:wojIIPWersja>2017-10-10T00:00:00+02:00</sln:wojIIPWersja><sln:wojIdTeryt>12</sln:wojIdTeryt><sln:wojNazwa>małopolskie</sln:wojNazwa></sln:miejscowosc><sln:miejscowosc><sln:cyklZyciaOd>2017-04-21T00:00:00+02:00</sln:cyklZyciaOd><sln:gmIIPId>fef90d5f-eb23-4381-bcde-f50bc3f1cf0f</sln:gmIIPId><sln:gmIIPPn>PL.PZGIK.200</sln:gmIIPPn><sln:gmIIPWersja>2012-09-26T22:11:56+02:00</sln:gmIIPWersja><sln:gmIdTeryt>1214012</sln:gmIdTeryt><sln:gmNazwa>Koniusza</sln:gmNazwa><sln:miejscIIPId>f7da0305-d074-4d60-bb33-7b94657556cc</sln:miejscIIPId><sln:miejscIIPPn>PL.PZGIK.200</sln:miejscIIPPn><sln:miejscIIPWersja>2017-04-21T14:09:37+02:00</sln:miejscIIPWersja><sln:miejscIdTeryt>0324027</sln:miejscIdTeryt><sln:miejscNazwa>Zielona</sln:miejscNazwa><sln:miejscRodzaj>Wieś</sln:miejscRodzaj><sln:powIIPId>adb95dd1-f39a-46c3-a2ee-c5dfb69b1d25</sln:powIIPId><sln:powIIPPn>PL.PZGIK.200</sln:powIIPPn><sln:powIIPWersja>2012-09-27T07:52:00+02:00</sln:powIIPWersja><sln:powIdTeryt>1214</sln:powIdTeryt><sln:powNazwa>proszowicki</sln:powNazwa><sln:waznyOd>2015-12-23T00:00:00+01:00</sln:waznyOd><sln:wojIIPId>dd2e3c64-f861-47cf-a3a3-e7751f272b2f</sln:wojIIPId><sln:wojIIPPn>PL.PZGIK.200</sln:wojIIPPn><sln:wojIIPWersja>2017-10-10T00:00:00+02:00</sln:wojIIPWersja><sln:wojIdTeryt>12</sln:wojIdTeryt><sln:wojNazwa>małopolskie</sln:wojNazwa></sln:miejscowosc></sln:lista-miejscowosci>