<?xml version="1.0" encoding="UTF-8" standalone="yes"?><sln:lista-miejscowosci xmlns:srv="http://gugik.gov.pl/schemas/slowniki-service/1.0" xmlns:sln="http://gugik.gov.pl/schemas/slowniki-schema/1.0"><sln:miejscowosc><sln:cyklZyciaOd>2014-11-26T00:00:00+01:00</sln:cyklZyciaOd><sln:gmIIPId>0c830835-1f11-4999-be09-bf52c1adb7b1</sln:gmIIPId><sln:gmIIPPn>PL.PZGIK.200</sln:gmIIPPn><sln:gmIIPWersja>2012-09-26T22:14:34+02:00</sln:gmIIPWersja><sln:gmIdTeryt>1263011</sln:gmIdTeryt><sln:gmNazwa>Tarnów</sln:gmNazwa><sln:miejscIIPId>a59f1af1-2163-4195-bc29-70029e33bbec</sln:miejscIIPId><sln:miejscIIPPn>PL.PZGIK.200</sln:miejscIIPPn><sln:miejscIIPWersja>2016-11-24T13:32:15+02:00</sln:miejscIIPWersja><sln:miejscIdTeryt>0981570</sln:miejscIdTeryt><sln:miejscNazwa>Tarnów</sln:miejscNazwa><sln:miejscRodzaj>Miasto</sln:miejscRodzaj><sln:powIIPId>445d2b9f-72f1-48e9-8bde-cf1bd8cbfa80</sln:powIIPId><sln:powIIPPn>PL.PZGIK.200</sln:powIIPPn><sln:powIIPWersja>2012-09-27T07:52:01+02:00</sln:powIIPWersja><sln:powIdTeryt>1263</sln:powIdTeryt><sln:powNazwa>Tarnów</sln:powNazwa><sln:wojIIPId>dd2e3c64-f861-47cf-a3a3-e7751f272b2f</sln:wojIIPId><sln:wojIIPPn>PL.PZGIK.200</sln:wojIIPPn><sln:wojIIPWersja>2017-10-10T00:00:00+02:00</sln:wojIIPWersja><sln:wojIdTeryt>12</sln:wojIdTeryt><sln:wojNazwa>małopolskie</sln:wojNazwa></sln:miejscowosc></sln:lista-miejscowosci>